{
"meta":{"test_sets":[],"test_metrics":[],"learn_metrics":[{"best_value":"Min","name":"RMSE"}],"launch_mode":"Train","parameters":"","iteration_count":1000,"learn_sets":["learn"],"name":"experiment"},
"iterations":[
{"learn":[14.59871775],"iteration":0,"passed_time":0.05754149164,"remaining_time":57.48395014},
{"learn":[14.22518863],"iteration":1,"passed_time":0.0577569902,"remaining_time":28.82073811},
{"learn":[13.8866124],"iteration":2,"passed_time":0.05799015531,"remaining_time":19.27206162},
{"learn":[13.52356875],"iteration":3,"passed_time":0.05818077904,"remaining_time":14.48701398},
{"learn":[13.18870211],"iteration":4,"passed_time":0.05837861106,"remaining_time":11.6173436},
{"learn":[12.9124226],"iteration":5,"passed_time":0.05856940145,"remaining_time":9.702997508},
{"learn":[12.60003351],"iteration":6,"passed_time":0.05880631654,"remaining_time":8.342096047},
{"learn":[12.32990573],"iteration":7,"passed_time":0.05899223197,"remaining_time":7.315036764},
{"learn":[12.0660619],"iteration":8,"passed_time":0.05917893906,"remaining_time":6.516258734},
{"learn":[11.77309809],"iteration":9,"passed_time":0.05938335436,"remaining_time":5.878952082},
{"learn":[11.49227636],"iteration":10,"passed_time":0.0595831447,"remaining_time":5.357066373},
{"learn":[11.26264833],"iteration":11,"passed_time":0.05979172664,"remaining_time":4.92285216},
{"learn":[11.04260393],"iteration":12,"passed_time":0.06008201638,"remaining_time":4.561611551},
{"learn":[10.79916926],"iteration":13,"passed_time":0.06029951493,"remaining_time":4.246808694},
{"learn":[10.5541002],"iteration":14,"passed_time":0.06051563849,"remaining_time":3.973860261},
{"learn":[10.31918115],"iteration":15,"passed_time":0.06074272031,"remaining_time":3.735677299},
{"learn":[10.10004441],"iteration":16,"passed_time":0.06096059386,"remaining_time":3.524956692},
{"learn":[9.894556723],"iteration":17,"passed_time":0.06119267564,"remaining_time":3.338400416},
{"learn":[9.690174082],"iteration":18,"passed_time":0.06139521596,"remaining_time":3.16993194},
{"learn":[9.506034866],"iteration":19,"passed_time":0.06159704795,"remaining_time":3.01825535},
{"learn":[9.338524633],"iteration":20,"passed_time":0.06188375437,"remaining_time":2.884961692},
{"learn":[9.170203312],"iteration":21,"passed_time":0.06213529436,"remaining_time":2.762196268},
{"learn":[9.010299969],"iteration":22,"passed_time":0.06235183459,"remaining_time":2.648597495},
{"learn":[8.843866678],"iteration":23,"passed_time":0.06254154166,"remaining_time":2.543356027},
{"learn":[8.690548059],"iteration":24,"passed_time":0.06274349864,"remaining_time":2.446996447},
{"learn":[8.555307687],"iteration":25,"passed_time":0.06295320558,"remaining_time":2.358323932},
{"learn":[8.413851302],"iteration":26,"passed_time":0.06314241265,"remaining_time":2.275465463},
{"learn":[8.29256019],"iteration":27,"passed_time":0.06334470297,"remaining_time":2.198966117},
{"learn":[8.162193833],"iteration":28,"passed_time":0.06359386798,"remaining_time":2.129298131},
{"learn":[8.040736294],"iteration":29,"passed_time":0.06384644963,"remaining_time":2.064368538},
{"learn":[7.921220278],"iteration":30,"passed_time":0.06404482331,"remaining_time":2.001917219},
{"learn":[7.809589039],"iteration":31,"passed_time":0.06424965528,"remaining_time":1.943552072},
{"learn":[7.699675801],"iteration":32,"passed_time":0.06443536237,"remaining_time":1.888151376},
{"learn":[7.60645267],"iteration":33,"passed_time":0.06466244419,"remaining_time":1.83717415},
{"learn":[7.498880302],"iteration":34,"passed_time":0.06484465131,"remaining_time":1.787859672},
{"learn":[7.401158744],"iteration":35,"passed_time":0.06502535844,"remaining_time":1.741234598},
{"learn":[7.306431077],"iteration":36,"passed_time":0.0652215238,"remaining_time":1.697522363},
{"learn":[7.223863468],"iteration":37,"passed_time":0.06543573071,"remaining_time":1.656557183},
{"learn":[7.143477682],"iteration":38,"passed_time":0.06566035421,"remaining_time":1.617938472},
{"learn":[7.062817131],"iteration":39,"passed_time":0.06584726963,"remaining_time":1.580334471},
{"learn":[6.990793435],"iteration":40,"passed_time":0.06603031008,"remaining_time":1.544465058},
{"learn":[6.931862224],"iteration":41,"passed_time":0.06622718377,"remaining_time":1.510610525},
{"learn":[6.858296558],"iteration":42,"passed_time":0.06644597398,"remaining_time":1.478809235},
{"learn":[6.786268161],"iteration":43,"passed_time":0.06662672277,"remaining_time":1.447616977},
{"learn":[6.717118549],"iteration":44,"passed_time":0.06679767997,"remaining_time":1.417595208},
{"learn":[6.652948106],"iteration":45,"passed_time":0.066992262,"remaining_time":1.38936126},
{"learn":[6.589686076],"iteration":46,"passed_time":0.06717155248,"remaining_time":1.362010415},
{"learn":[6.531283097],"iteration":47,"passed_time":0.06744042568,"remaining_time":1.337568443},
{"learn":[6.471368031],"iteration":48,"passed_time":0.06762800777,"remaining_time":1.312535416},
{"learn":[6.416481395],"iteration":49,"passed_time":0.06782350647,"remaining_time":1.288646623},
{"learn":[6.369870822],"iteration":50,"passed_time":0.06810004629,"remaining_time":1.267194979},
{"learn":[6.325678067],"iteration":51,"passed_time":0.06839212768,"remaining_time":1.246841097},
{"learn":[6.275766122],"iteration":52,"passed_time":0.06862116782,"remaining_time":1.226117848},
{"learn":[6.224773967],"iteration":53,"passed_time":0.06880779157,"remaining_time":1.205410571},
{"learn":[6.182249254],"iteration":54,"passed_time":0.06900749858,"remaining_time":1.185674294},
{"learn":[6.139904173],"iteration":55,"passed_time":0.06920783058,"remaining_time":1.166646287},
{"learn":[6.100525536],"iteration":56,"passed_time":0.06939632932,"remaining_time":1.148083132},
{"learn":[6.062568564],"iteration":57,"passed_time":0.06961532786,"remaining_time":1.130648946},
{"learn":[6.030559288],"iteration":58,"passed_time":0.06984349301,"remaining_time":1.113944524},
{"learn":[5.997931376],"iteration":59,"passed_time":0.07008878304,"remaining_time":1.098057601},
{"learn":[5.964103835],"iteration":60,"passed_time":0.07029794831,"remaining_time":1.082127434},
{"learn":[5.933729724],"iteration":61,"passed_time":0.07049015537,"remaining_time":1.066447834},
{"learn":[5.901932711],"iteration":62,"passed_time":0.07067215415,"remaining_time":1.051108071},
{"learn":[5.873727795],"iteration":63,"passed_time":0.0708698195,"remaining_time":1.03647111},
{"learn":[5.846485734],"iteration":64,"passed_time":0.07106927651,"remaining_time":1.022304208},
{"learn":[5.820630862],"iteration":65,"passed_time":0.07127406681,"remaining_time":1.008636036},
{"learn":[5.793646238],"iteration":66,"passed_time":0.07146735719,"remaining_time":0.9952096158},
{"learn":[5.765388646],"iteration":67,"passed_time":0.07164256436,"remaining_time":0.9819245585},
{"learn":[5.747073912],"iteration":68,"passed_time":0.07182677146,"remaining_time":0.9691409309},
{"learn":[5.722315217],"iteration":69,"passed_time":0.07201810352,"remaining_time":0.9568119468},
{"learn":[5.699970599],"iteration":70,"passed_time":0.07220018564,"remaining_time":0.9447038375},
{"learn":[5.682732647],"iteration":71,"passed_time":0.07239055937,"remaining_time":0.9330338763},
{"learn":[5.663525791],"iteration":72,"passed_time":0.07257464148,"remaining_time":0.9215985295},
{"learn":[5.642381613],"iteration":73,"passed_time":0.07274318202,"remaining_time":0.9102727913},
{"learn":[5.621404779],"iteration":74,"passed_time":0.0729158892,"remaining_time":0.8992959669},
{"learn":[5.602460129],"iteration":75,"passed_time":0.07311367955,"remaining_time":0.8889084198},
{"learn":[5.587337574],"iteration":76,"passed_time":0.07331426155,"remaining_time":0.8788190053},
{"learn":[5.572393026],"iteration":77,"passed_time":0.07352796846,"remaining_time":0.8691382939},
{"learn":[5.558425806],"iteration":78,"passed_time":0.07370684227,"remaining_time":0.8592911611},
{"learn":[5.541518902],"iteration":79,"passed_time":0.07389954932,"remaining_time":0.8498448172},
{"learn":[5.526157283],"iteration":80,"passed_time":0.0740819231,"remaining_time":0.8405097201},
{"learn":[5.511746977],"iteration":81,"passed_time":0.07426604688,"remaining_time":0.8314174516},
{"learn":[5.504975022],"iteration":82,"passed_time":0.07433654641,"remaining_time":0.8212844946},
{"learn":[5.493980522],"iteration":83,"passed_time":0.07451617021,"remaining_time":0.8125810942},
{"learn":[5.480745463],"iteration":84,"passed_time":0.07468891906,"remaining_time":0.8040042463},
{"learn":[5.464052013],"iteration":85,"passed_time":0.07487212617,"remaining_time":0.7957339921},
{"learn":[5.449143727],"iteration":86,"passed_time":0.07505420829,"remaining_time":0.787637841},
{"learn":[5.438255432],"iteration":87,"passed_time":0.0752327071,"remaining_time":0.7796844191},
{"learn":[5.425927931],"iteration":88,"passed_time":0.07543508075,"remaining_time":0.7721500963},
{"learn":[5.412331217],"iteration":89,"passed_time":0.07564270437,"remaining_time":0.7648317886},
{"learn":[5.400691499],"iteration":90,"passed_time":0.07591241091,"remaining_time":0.7582899068},
{"learn":[5.391618744],"iteration":91,"passed_time":0.07619111738,"remaining_time":0.751973202},
{"learn":[5.380766572],"iteration":92,"passed_time":0.07639653268,"remaining_time":0.7450715607},
{"learn":[5.372207183],"iteration":93,"passed_time":0.07663219778,"remaining_time":0.7386039488},
{"learn":[5.362918837],"iteration":94,"passed_time":0.07688244611,"remaining_time":0.7324064603},
{"learn":[5.348292324],"iteration":95,"passed_time":0.07714548603,"remaining_time":0.7264533267},
{"learn":[5.339772295],"iteration":96,"passed_time":0.07732510983,"remaining_time":0.7198409709},
{"learn":[5.331515983],"iteration":97,"passed_time":0.0775145669,"remaining_time":0.7134504015},
{"learn":[5.323861644],"iteration":98,"passed_time":0.07775706528,"remaining_time":0.7076678366},
{"learn":[5.313277281],"iteration":99,"passed_time":0.07799806368,"remaining_time":0.7019825731},
{"learn":[5.30685627],"iteration":100,"passed_time":0.07818868741,"remaining_time":0.6959567325},
{"learn":[5.29652059],"iteration":101,"passed_time":0.07841097759,"remaining_time":0.6903240969},
{"learn":[5.288350766],"iteration":102,"passed_time":0.07859851801,"remaining_time":0.6844938899},
{"learn":[5.27993346],"iteration":103,"passed_time":0.07879372504,"remaining_time":0.6788382465},
{"learn":[5.271789139],"iteration":104,"passed_time":0.07903309845,"remaining_time":0.6736630773},
{"learn":[5.262684686],"iteration":105,"passed_time":0.07922447217,"remaining_time":0.6681762087},
{"learn":[5.251619772],"iteration":106,"passed_time":0.07941422091,"remaining_time":0.6627747596},
{"learn":[5.241012171],"iteration":107,"passed_time":0.07960388631,"remaining_time":0.6574691351},
{"learn":[5.232684032],"iteration":108,"passed_time":0.07980642663,"remaining_time":0.652362625},
{"learn":[5.224267141],"iteration":109,"passed_time":0.07999863368,"remaining_time":0.6472616725},
{"learn":[5.216324968],"iteration":110,"passed_time":0.0801760075,"remaining_time":0.6421303664},
{"learn":[5.211102527],"iteration":111,"passed_time":0.08037021454,"remaining_time":0.6372209867},
{"learn":[5.206364257],"iteration":112,"passed_time":0.08053933841,"remaining_time":0.6321981697},
{"learn":[5.196937641],"iteration":113,"passed_time":0.08072600384,"remaining_time":0.6273968368},
{"learn":[5.190746047],"iteration":114,"passed_time":0.08090350265,"remaining_time":0.6226052161},
{"learn":[5.181885213],"iteration":115,"passed_time":0.0810719182,"remaining_time":0.6178239283},
{"learn":[5.178293568],"iteration":116,"passed_time":0.08121062561,"remaining_time":0.6128972856},
{"learn":[5.170991438],"iteration":117,"passed_time":0.08140545764,"remaining_time":0.6084713021},
{"learn":[5.166257212],"iteration":118,"passed_time":0.08159491472,"remaining_time":0.6040766375},
{"learn":[5.161421246],"iteration":119,"passed_time":0.08177558018,"remaining_time":0.599687588},
{"learn":[5.158223542],"iteration":120,"passed_time":0.08195841229,"remaining_time":0.5953838381},
{"learn":[5.15470988],"iteration":121,"passed_time":0.08208461979,"remaining_time":0.5907401326},
{"learn":[5.146388143],"iteration":122,"passed_time":0.08229520172,"remaining_time":0.5867714789},
{"learn":[5.139529364],"iteration":123,"passed_time":0.08248307546,"remaining_time":0.582703017},
{"learn":[5.134276023],"iteration":124,"passed_time":0.08268419912,"remaining_time":0.5787893939},
{"learn":[5.128536065],"iteration":125,"passed_time":0.08288248947,"remaining_time":0.574915046},
{"learn":[5.123300353],"iteration":126,"passed_time":0.0830080303,"remaining_time":0.5705985075},
{"learn":[5.116200518],"iteration":127,"passed_time":0.08318557078,"remaining_time":0.566701701},
{"learn":[5.108728704],"iteration":128,"passed_time":0.08340511099,"remaining_time":0.563146137},
{"learn":[5.104075866],"iteration":129,"passed_time":0.0835881931,"remaining_time":0.5593979077},
{"learn":[5.100317606],"iteration":130,"passed_time":0.08376631692,"remaining_time":0.5556712168},
{"learn":[5.095814182],"iteration":131,"passed_time":0.08393627412,"remaining_time":0.5519445904},
{"learn":[5.092146915],"iteration":132,"passed_time":0.0841693559,"remaining_time":0.5486829441},
{"learn":[5.085258329],"iteration":133,"passed_time":0.08435135468,"remaining_time":0.5451363668},
{"learn":[5.079219421],"iteration":134,"passed_time":0.08452127022,"remaining_time":0.5415622129},
{"learn":[5.076476829],"iteration":135,"passed_time":0.08470485233,"remaining_time":0.5381249442},
{"learn":[5.072133867],"iteration":136,"passed_time":0.08491139262,"remaining_time":0.5348797944},
{"learn":[5.067031564],"iteration":137,"passed_time":0.08510176635,"remaining_time":0.5315777},
{"learn":[5.061358312],"iteration":138,"passed_time":0.08528334847,"remaining_time":0.5282659211},
{"learn":[5.056759124],"iteration":139,"passed_time":0.08547468053,"remaining_time":0.5250587518},
{"learn":[5.050254],"iteration":140,"passed_time":0.08570680399,"remaining_time":0.5221428697},
{"learn":[5.048376474],"iteration":141,"passed_time":0.08580251168,"remaining_time":0.5184405283},
{"learn":[5.042603751],"iteration":142,"passed_time":0.0860003437,"remaining_time":0.5154006612},
{"learn":[5.037477349],"iteration":143,"passed_time":0.08617480087,"remaining_time":0.5122613163},
{"learn":[5.03230489],"iteration":144,"passed_time":0.0863600913,"remaining_time":0.5092267453},
{"learn":[5.025976187],"iteration":145,"passed_time":0.08655067336,"remaining_time":0.5062621579},
{"learn":[5.01952451],"iteration":146,"passed_time":0.08674083876,"remaining_time":0.5033328943},
{"learn":[5.017569424],"iteration":147,"passed_time":0.0869105043,"remaining_time":0.5003226329},
{"learn":[5.008962367],"iteration":148,"passed_time":0.08709616973,"remaining_time":0.4974418822},
{"learn":[5.003880266],"iteration":149,"passed_time":0.08726858525,"remaining_time":0.4945219831},
{"learn":[4.996387564],"iteration":150,"passed_time":0.08746387561,"remaining_time":0.4917670887},
{"learn":[4.993361683],"iteration":151,"passed_time":0.08764370775,"remaining_time":0.4889596327},
{"learn":[4.99005752],"iteration":152,"passed_time":0.08793028917,"remaining_time":0.4867774832},
{"learn":[4.986908764],"iteration":153,"passed_time":0.08821841225,"remaining_time":0.4846284206},
{"learn":[4.985207175],"iteration":154,"passed_time":0.08846036897,"remaining_time":0.4822516889},
{"learn":[4.979003494],"iteration":155,"passed_time":0.08868290916,"remaining_time":0.4797972778},
{"learn":[4.973142217],"iteration":156,"passed_time":0.08890132437,"remaining_time":0.4773491493},
{"learn":[4.967056696],"iteration":157,"passed_time":0.08911261463,"remaining_time":0.4748912754},
{"learn":[4.961460696],"iteration":158,"passed_time":0.08930061338,"remaining_time":0.4723384645},
{"learn":[4.954240363],"iteration":159,"passed_time":0.08947061224,"remaining_time":0.4697207143},
{"learn":[4.952320707],"iteration":160,"passed_time":0.08955332003,"remaining_time":0.4666784814},
{"learn":[4.948337777],"iteration":161,"passed_time":0.0897326105,"remaining_time":0.4641723926},
{"learn":[4.943228639],"iteration":162,"passed_time":0.08990548435,"remaining_time":0.4616619043},
{"learn":[4.938545759],"iteration":163,"passed_time":0.09008969145,"remaining_time":0.4592376955},
{"learn":[4.935330572],"iteration":164,"passed_time":0.09025498202,"remaining_time":0.456744909},
{"learn":[4.932051543],"iteration":165,"passed_time":0.0904275642,"remaining_time":0.4543167985},
{"learn":[4.928964153],"iteration":166,"passed_time":0.09059402143,"remaining_time":0.4518851488},
{"learn":[4.922860227],"iteration":167,"passed_time":0.09076918693,"remaining_time":0.4495235924},
{"learn":[4.917668772],"iteration":168,"passed_time":0.09098568548,"remaining_time":0.4473911517},
{"learn":[4.910365386],"iteration":169,"passed_time":0.09125118371,"remaining_time":0.4455204852},
{"learn":[4.906457206],"iteration":170,"passed_time":0.09145939066,"remaining_time":0.4433908471},
{"learn":[4.901996508],"iteration":171,"passed_time":0.0916430561,"remaining_time":0.4411654096},
{"learn":[4.896816173],"iteration":172,"passed_time":0.09184034646,"remaining_time":0.4390287082},
{"learn":[4.891123132],"iteration":173,"passed_time":0.0920285952,"remaining_time":0.4368713772},
{"learn":[4.887630202],"iteration":174,"passed_time":0.09221363564,"remaining_time":0.4347214251},
{"learn":[4.885259712],"iteration":175,"passed_time":0.09244163412,"remaining_time":0.4327949234},
{"learn":[4.880659728],"iteration":176,"passed_time":0.09267188258,"remaining_time":0.4308980755},
{"learn":[4.877299723],"iteration":177,"passed_time":0.0928645063,"remaining_time":0.4288462032},
{"learn":[4.874038772],"iteration":178,"passed_time":0.09303883847,"remaining_time":0.4267312089},
{"learn":[4.86943698],"iteration":179,"passed_time":0.0932140873,"remaining_time":0.4246419533},
{"learn":[4.861268711],"iteration":180,"passed_time":0.09340346104,"remaining_time":0.4226377602},
{"learn":[4.858673056],"iteration":181,"passed_time":0.09366487597,"remaining_time":0.4209772997},
{"learn":[4.854036207],"iteration":182,"passed_time":0.09389595776,"remaining_time":0.4191967076},
{"learn":[4.85130244],"iteration":183,"passed_time":0.09407328991,"remaining_time":0.41719459},
{"learn":[4.847510084],"iteration":184,"passed_time":0.0942649553,"remaining_time":0.4152753436},
{"learn":[4.845691673],"iteration":185,"passed_time":0.09444091246,"remaining_time":0.4133059287},
{"learn":[4.842058646],"iteration":186,"passed_time":0.09462603623,"remaining_time":0.4113955479},
{"learn":[4.838623675],"iteration":187,"passed_time":0.09480845168,"remaining_time":0.4094918232},
{"learn":[4.834602161],"iteration":188,"passed_time":0.09499036714,"remaining_time":0.407604168},
{"learn":[4.830858976],"iteration":189,"passed_time":0.09519224079,"remaining_time":0.4058195528},
{"learn":[4.827590511],"iteration":190,"passed_time":0.09537119793,"remaining_time":0.4039544457},
{"learn":[4.822246226],"iteration":191,"passed_time":0.09556061334,"remaining_time":0.4021509145},
{"learn":[4.816686395],"iteration":192,"passed_time":0.09573986214,"remaining_time":0.4003215997},
{"learn":[4.814797121],"iteration":193,"passed_time":0.09593048587,"remaining_time":0.3985565547},
{"learn":[4.811639392],"iteration":194,"passed_time":0.09609410978,"remaining_time":0.3966961968},
{"learn":[4.804813432],"iteration":195,"passed_time":0.09627377525,"remaining_time":0.3949189556},
{"learn":[4.80251613],"iteration":196,"passed_time":0.09644744076,"remaining_time":0.3931334768},
{"learn":[4.800087884],"iteration":197,"passed_time":0.09664810609,"remaining_time":0.3914736418},
{"learn":[4.794773135],"iteration":198,"passed_time":0.09687043794,"remaining_time":0.3899156824},
{"learn":[4.791664833],"iteration":199,"passed_time":0.09704910342,"remaining_time":0.3881964137},
{"learn":[4.785989873],"iteration":200,"passed_time":0.0972366855,"remaining_time":0.386527919},
{"learn":[4.782387142],"iteration":201,"passed_time":0.09743422585,"remaining_time":0.3849134269},
{"learn":[4.778623704],"iteration":202,"passed_time":0.0976330162,"remaining_time":0.3833178025},
{"learn":[4.775772178],"iteration":203,"passed_time":0.09780339006,"remaining_time":0.3816249926},
{"learn":[4.77023101],"iteration":204,"passed_time":0.09801418032,"remaining_time":0.3801037725},
{"learn":[4.764496689],"iteration":205,"passed_time":0.09819622078,"remaining_time":0.3784844626},
{"learn":[4.763138716],"iteration":206,"passed_time":0.0984281359,"remaining_time":0.3770701052},
{"learn":[4.758053283],"iteration":207,"passed_time":0.09860830137,"remaining_time":0.3754700706},
{"learn":[4.755063788],"iteration":208,"passed_time":0.09880188341,"remaining_time":0.3739344008},
{"learn":[4.752465267],"iteration":209,"passed_time":0.09897267394,"remaining_time":0.3723257734},
{"learn":[4.748067377],"iteration":210,"passed_time":0.09914396446,"remaining_time":0.3707326444},
{"learn":[4.744163298],"iteration":211,"passed_time":0.09934067149,"remaining_time":0.3692474016},
{"learn":[4.736670896],"iteration":212,"passed_time":0.09952492026,"remaining_time":0.3677282265},
{"learn":[4.73349255],"iteration":213,"passed_time":0.09970508572,"remaining_time":0.3662065298},
{"learn":[4.731864595],"iteration":214,"passed_time":0.09987279294,"remaining_time":0.3646518254},
{"learn":[4.728398311],"iteration":215,"passed_time":0.100058125,"remaining_time":0.3631739353},
{"learn":[4.723865975],"iteration":216,"passed_time":0.1002516237,"remaining_time":0.3617374258},
{"learn":[4.723483365],"iteration":217,"passed_time":0.1004379975,"remaining_time":0.3602867617},
{"learn":[4.72095416],"iteration":218,"passed_time":0.100664121,"remaining_time":0.3589893996},
{"learn":[4.716173382],"iteration":219,"passed_time":0.100870953,"remaining_time":0.3576333787},
{"learn":[4.710563974],"iteration":220,"passed_time":0.1010534101,"remaining_time":0.3562018391},
{"learn":[4.707160263],"iteration":221,"passed_time":0.1013111167,"remaining_time":0.3550452648},
{"learn":[4.70408351],"iteration":222,"passed_time":0.1015070321,"remaining_time":0.3536814525},
{"learn":[4.702501831],"iteration":223,"passed_time":0.1016777809,"remaining_time":0.3522408839},
{"learn":[4.700269738],"iteration":224,"passed_time":0.1018570714,"remaining_time":0.3508410237},
{"learn":[4.695346302],"iteration":225,"passed_time":0.1020258619,"remaining_time":0.349416005},
{"learn":[4.689769299],"iteration":226,"passed_time":0.1022204856,"remaining_time":0.3480900238},
{"learn":[4.687919514],"iteration":227,"passed_time":0.102414776,"remaining_time":0.3467728381},
{"learn":[4.682982074],"iteration":228,"passed_time":0.1025811916,"remaining_time":0.34537161},
{"learn":[4.679578702],"iteration":229,"passed_time":0.1027706903,"remaining_time":0.344058398},
{"learn":[4.675751423],"iteration":230,"passed_time":0.1029543974,"remaining_time":0.3427356347},
{"learn":[4.672710726],"iteration":231,"passed_time":0.1031398962,"remaining_time":0.3414286218},
{"learn":[4.6690533],"iteration":232,"passed_time":0.1033394365,"remaining_time":0.3401774584},
{"learn":[4.667595702],"iteration":233,"passed_time":0.1035178937,"remaining_time":0.3388662673},
{"learn":[4.664241291],"iteration":234,"passed_time":0.1036964341,"remaining_time":0.3375649877},
{"learn":[4.662246999],"iteration":235,"passed_time":0.1038822246,"remaining_time":0.3362966931},
{"learn":[4.658668443],"iteration":236,"passed_time":0.1040696816,"remaining_time":0.3350428991},
{"learn":[4.658017572],"iteration":237,"passed_time":0.1042466388,"remaining_time":0.3337644486},
{"learn":[4.657656705],"iteration":238,"passed_time":0.1044206376,"remaining_time":0.332485796},
{"learn":[4.653242871],"iteration":239,"passed_time":0.1045918448,"remaining_time":0.3312075086},
{"learn":[4.6507302],"iteration":240,"passed_time":0.1047796769,"remaining_time":0.3299907667},
{"learn":[4.647671336],"iteration":241,"passed_time":0.104959759,"remaining_time":0.3287582536},
{"learn":[4.645506007],"iteration":242,"passed_time":0.1051434662,"remaining_time":0.327545695},
{"learn":[4.641297906],"iteration":243,"passed_time":0.1053420898,"remaining_time":0.3263877865},
{"learn":[4.63798107],"iteration":244,"passed_time":0.1055328386,"remaining_time":0.3252134413},
{"learn":[4.635062318],"iteration":245,"passed_time":0.1057299623,"remaining_time":0.3240666323},
{"learn":[4.631606017],"iteration":246,"passed_time":0.1059310859,"remaining_time":0.3229397073},
{"learn":[4.630215494],"iteration":247,"passed_time":0.1061681677,"remaining_time":0.3219292826},
{"learn":[4.62729814],"iteration":248,"passed_time":0.1064067077,"remaining_time":0.3209294679},
{"learn":[4.624691756],"iteration":249,"passed_time":0.1065840816,"remaining_time":0.3197522447},
{"learn":[4.621840053],"iteration":250,"passed_time":0.1067817052,"remaining_time":0.3186434152},
{"learn":[4.619602091],"iteration":251,"passed_time":0.1069814122,"remaining_time":0.3175480014},
{"learn":[4.613584029],"iteration":252,"passed_time":0.1071833276,"remaining_time":0.3164661885},
{"learn":[4.6119388],"iteration":253,"passed_time":0.1073737013,"remaining_time":0.3153574062},
{"learn":[4.60870702],"iteration":254,"passed_time":0.1076175747,"remaining_time":0.3144121299},
{"learn":[4.604771557],"iteration":255,"passed_time":0.1078466148,"remaining_time":0.3134292243},
{"learn":[4.604231277],"iteration":256,"passed_time":0.10806628,"remaining_time":0.3124250819},
{"learn":[4.600750354],"iteration":257,"passed_time":0.1082605287,"remaining_time":0.3113539237},
{"learn":[4.596488253],"iteration":258,"passed_time":0.1084495691,"remaining_time":0.310274636},
{"learn":[4.59470784],"iteration":259,"passed_time":0.1086298179,"remaining_time":0.3091771741},
{"learn":[4.588818005],"iteration":260,"passed_time":0.108821025,"remaining_time":0.3081177681},
{"learn":[4.585054174],"iteration":261,"passed_time":0.1090024821,"remaining_time":0.307037526},
{"learn":[4.581471435],"iteration":262,"passed_time":0.1091798976,"remaining_time":0.3059527929},
{"learn":[4.577555199],"iteration":263,"passed_time":0.1093793129,"remaining_time":0.3049362664},
{"learn":[4.57457145],"iteration":264,"passed_time":0.1095684367,"remaining_time":0.3038973621},
{"learn":[4.573029224],"iteration":265,"passed_time":0.1097415605,"remaining_time":0.3028206971},
{"learn":[4.571326203],"iteration":266,"passed_time":0.1099131844,"remaining_time":0.3017466822},
{"learn":[4.571019224],"iteration":267,"passed_time":0.1100978915,"remaining_time":0.3007151364},
{"learn":[4.565766631],"iteration":268,"passed_time":0.1102866819,"remaining_time":0.2997009831},
{"learn":[4.563383471],"iteration":269,"passed_time":0.1104655974,"remaining_time":0.2986662447},
{"learn":[4.558165805],"iteration":270,"passed_time":0.1106538878,"remaining_time":0.2976630413},
{"learn":[4.55629209],"iteration":271,"passed_time":0.1108368449,"remaining_time":0.2966515555},
{"learn":[4.549383848],"iteration":272,"passed_time":0.1110231353,"remaining_time":0.295655016},
{"learn":[4.546227503],"iteration":273,"passed_time":0.111218259,"remaining_time":0.2946877958},
{"learn":[4.540620977],"iteration":274,"passed_time":0.1115535901,"remaining_time":0.2940958285},
{"learn":[4.532898237],"iteration":275,"passed_time":0.1119821706,"remaining_time":0.2937503316},
{"learn":[4.529757367],"iteration":276,"passed_time":0.1122040858,"remaining_time":0.292864816},
{"learn":[4.52579294],"iteration":277,"passed_time":0.1125013338,"remaining_time":0.292179723},
{"learn":[4.521572155],"iteration":278,"passed_time":0.1127776653,"remaining_time":0.2914433573},
{"learn":[4.518818099],"iteration":279,"passed_time":0.1130546635,"remaining_time":0.2907119917},
{"learn":[4.514012334],"iteration":280,"passed_time":0.1132678287,"remaining_time":0.2898205297},
{"learn":[4.508331416],"iteration":281,"passed_time":0.1134381192,"remaining_time":0.2888247149},
{"learn":[4.506038537],"iteration":282,"passed_time":0.1136546178,"remaining_time":0.2879518055},
{"learn":[4.505805643],"iteration":283,"passed_time":0.1138670747,"remaining_time":0.2870733292},
{"learn":[4.501550352],"iteration":284,"passed_time":0.1140821566,"remaining_time":0.2862061122},
{"learn":[4.494692643],"iteration":285,"passed_time":0.1142943219,"remaining_time":0.2853361742},
{"learn":[4.489330245],"iteration":286,"passed_time":0.114470529,"remaining_time":0.2843814885},
{"learn":[4.484826955],"iteration":287,"passed_time":0.1146703194,"remaining_time":0.2834905117},
{"learn":[4.478285428],"iteration":288,"passed_time":0.1148419849,"remaining_time":0.2825351254},
{"learn":[4.475311671],"iteration":289,"passed_time":0.1150870666,"remaining_time":0.2817648871},
{"learn":[4.471581298],"iteration":290,"passed_time":0.1152602321,"remaining_time":0.2808230397},
{"learn":[4.469164956],"iteration":291,"passed_time":0.1154357309,"remaining_time":0.2798921147},
{"learn":[4.462068024],"iteration":292,"passed_time":0.1156239797,"remaining_time":0.2789971113},
{"learn":[4.458540976],"iteration":293,"passed_time":0.115820645,"remaining_time":0.2781271272},
{"learn":[4.455757458],"iteration":294,"passed_time":0.1160109354,"remaining_time":0.2772464728},
{"learn":[4.453027414],"iteration":295,"passed_time":0.1162023091,"remaining_time":0.2763730596},
{"learn":[4.450659338],"iteration":296,"passed_time":0.1163965162,"remaining_time":0.2755109457},
{"learn":[4.444696901],"iteration":297,"passed_time":0.1167084724,"remaining_time":0.2749306968},
{"learn":[4.442052813],"iteration":298,"passed_time":0.1169036378,"remaining_time":0.2740784284},
{"learn":[4.440036756],"iteration":299,"passed_time":0.1170726783,"remaining_time":0.2731695828},
{"learn":[4.435017051],"iteration":300,"passed_time":0.1172843853,"remaining_time":0.2723647352},
{"learn":[4.429962125],"iteration":301,"passed_time":0.1175005922,"remaining_time":0.2715742163},
{"learn":[4.427666256],"iteration":302,"passed_time":0.1177035908,"remaining_time":0.2707571049},
{"learn":[4.425030004],"iteration":303,"passed_time":0.1178925062,"remaining_time":0.2699117906},
{"learn":[4.422588771],"iteration":304,"passed_time":0.118076255,"remaining_time":0.2690590073},
{"learn":[4.418936667],"iteration":305,"passed_time":0.1182545455,"remaining_time":0.2681982175},
{"learn":[4.416887976],"iteration":306,"passed_time":0.1184247943,"remaining_time":0.2673237214},
{"learn":[4.413773354],"iteration":307,"passed_time":0.1186030848,"remaining_time":0.2664718659},
{"learn":[4.411129391],"iteration":308,"passed_time":0.1187794586,"remaining_time":0.2656200839},
{"learn":[4.40850819],"iteration":309,"passed_time":0.1189521658,"remaining_time":0.2647644981},
{"learn":[4.404880292],"iteration":310,"passed_time":0.1191413312,"remaining_time":0.263949766},
{"learn":[4.404593827],"iteration":311,"passed_time":0.1193261217,"remaining_time":0.2631293965},
{"learn":[4.402139942],"iteration":312,"passed_time":0.1195094121,"remaining_time":0.2623097959},
{"learn":[4.400284725],"iteration":313,"passed_time":0.1196945359,"remaining_time":0.2614982535},
{"learn":[4.395805521],"iteration":314,"passed_time":0.1198876179,"remaining_time":0.2607079945},
{"learn":[4.392838833],"iteration":315,"passed_time":0.1201047831,"remaining_time":0.2599736445},
{"learn":[4.389213061],"iteration":316,"passed_time":0.1202956152,"remaining_time":0.2591858208},
{"learn":[4.3861981],"iteration":317,"passed_time":0.1205406136,"remaining_time":0.2585179197},
{"learn":[4.385054234],"iteration":318,"passed_time":0.1208439449,"remaining_time":0.257977199},
{"learn":[4.379364607],"iteration":319,"passed_time":0.1211143598,"remaining_time":0.2573680145},
{"learn":[4.378387619],"iteration":320,"passed_time":0.1213473582,"remaining_time":0.2566817951},
{"learn":[4.375816727],"iteration":321,"passed_time":0.121533232,"remaining_time":0.2558991654},
{"learn":[4.374600202],"iteration":322,"passed_time":0.1217101058,"remaining_time":0.2551013672},
{"learn":[4.37098897],"iteration":323,"passed_time":0.1218942712,"remaining_time":0.2543226153},
{"learn":[4.367418484],"iteration":324,"passed_time":0.1221505195,"remaining_time":0.2536972328},
{"learn":[4.363584638],"iteration":325,"passed_time":0.1223368516,"remaining_time":0.2529295644},
{"learn":[4.360770706],"iteration":326,"passed_time":0.1225490585,"remaining_time":0.2522187046},
{"learn":[4.358675808],"iteration":327,"passed_time":0.1228368483,"remaining_time":0.2516657379},
{"learn":[4.354228195],"iteration":328,"passed_time":0.1230478885,"remaining_time":0.2509578517},
{"learn":[4.353773425],"iteration":329,"passed_time":0.1232375123,"remaining_time":0.2502094946},
{"learn":[4.351648009],"iteration":330,"passed_time":0.1235631351,"remaining_time":0.2497393879},
{"learn":[4.348209927],"iteration":331,"passed_time":0.1238762997,"remaining_time":0.2492450849},
{"learn":[4.345852733],"iteration":332,"passed_time":0.1241400063,"remaining_time":0.2486528053},
{"learn":[4.34237339],"iteration":333,"passed_time":0.1243514215,"remaining_time":0.2479582238},
{"learn":[4.340814362],"iteration":334,"passed_time":0.1245415869,"remaining_time":0.2472243442},
{"learn":[4.339707068],"iteration":335,"passed_time":0.1247402523,"remaining_time":0.2465104985},
{"learn":[4.335430786],"iteration":336,"passed_time":0.1249569175,"remaining_time":0.2458351225},
{"learn":[4.33521887],"iteration":337,"passed_time":0.1251438746,"remaining_time":0.2451042751},
{"learn":[4.328507238],"iteration":338,"passed_time":0.1253238734,"remaining_time":0.2443630687},
{"learn":[4.326140732],"iteration":339,"passed_time":0.1255692884,"remaining_time":0.2437521481},
{"learn":[4.323785636],"iteration":340,"passed_time":0.1257789537,"remaining_time":0.2430742829},
{"learn":[4.320632534],"iteration":341,"passed_time":0.1259910356,"remaining_time":0.2424038053},
{"learn":[4.31973724],"iteration":342,"passed_time":0.1261897426,"remaining_time":0.2417103816},
{"learn":[4.318000924],"iteration":343,"passed_time":0.126386408,"remaining_time":0.2410159408},
{"learn":[4.312713628],"iteration":344,"passed_time":0.1265749484,"remaining_time":0.24030896},
{"learn":[4.308220789],"iteration":345,"passed_time":0.126773947,"remaining_time":0.2396247438},
{"learn":[4.305890947],"iteration":346,"passed_time":0.126980029,"remaining_time":0.238956654},
{"learn":[4.305137856],"iteration":347,"passed_time":0.1271652361,"remaining_time":0.238252109},
{"learn":[4.304787172],"iteration":348,"passed_time":0.1273359433,"remaining_time":0.2375234931},
{"learn":[4.30350134],"iteration":349,"passed_time":0.1275076922,"remaining_time":0.2367999997},
{"learn":[4.30293809],"iteration":350,"passed_time":0.1276974826,"remaining_time":0.2361130091},
{"learn":[4.299548459],"iteration":351,"passed_time":0.1278899396,"remaining_time":0.2354337525},
{"learn":[4.294768408],"iteration":352,"passed_time":0.1280778967,"remaining_time":0.2347490061},
{"learn":[4.294581479],"iteration":353,"passed_time":0.1282582705,"remaining_time":0.2340532281},
{"learn":[4.292551604],"iteration":354,"passed_time":0.1284594358,"remaining_time":0.2333981299},
{"learn":[4.288628894],"iteration":355,"passed_time":0.1286575595,"remaining_time":0.2327400795},
{"learn":[4.287802767],"iteration":356,"passed_time":0.1288340583,"remaining_time":0.2320456569},
{"learn":[4.284566905],"iteration":357,"passed_time":0.129030932,"remaining_time":0.2313906658},
{"learn":[4.27890232],"iteration":358,"passed_time":0.1292469722,"remaining_time":0.230772449},
{"learn":[4.276938023],"iteration":359,"passed_time":0.1294423876,"remaining_time":0.2301198002},
{"learn":[4.273425094],"iteration":360,"passed_time":0.1296201781,"remaining_time":0.229438487},
{"learn":[4.269726505],"iteration":361,"passed_time":0.129840385,"remaining_time":0.2288347116},
{"learn":[4.265565857],"iteration":362,"passed_time":0.1300358836,"remaining_time":0.2281896911},
{"learn":[4.262117173],"iteration":363,"passed_time":0.1302180491,"remaining_time":0.227523844},
{"learn":[4.259185148],"iteration":364,"passed_time":0.1304043395,"remaining_time":0.2268678236},
{"learn":[4.257668507],"iteration":365,"passed_time":0.1305992132,"remaining_time":0.2262292382},
{"learn":[4.253432436],"iteration":366,"passed_time":0.1308003786,"remaining_time":0.2256039227},
{"learn":[4.250216667],"iteration":367,"passed_time":0.1309908773,"remaining_time":0.2249625936},
{"learn":[4.24514828],"iteration":368,"passed_time":0.131177126,"remaining_time":0.2243164405},
{"learn":[4.244015772],"iteration":369,"passed_time":0.1313477499,"remaining_time":0.2236461688},
{"learn":[4.240329192],"iteration":370,"passed_time":0.1315471652,"remaining_time":0.2230274042},
{"learn":[4.236718014],"iteration":371,"passed_time":0.1317304974,"remaining_time":0.2223837429},
{"learn":[4.233495944],"iteration":372,"passed_time":0.1319242044,"remaining_time":0.2217599897},
{"learn":[4.230357491],"iteration":373,"passed_time":0.1321122448,"remaining_time":0.2211290515},
{"learn":[4.227381215],"iteration":374,"passed_time":0.1324050762,"remaining_time":0.220675127},
{"learn":[4.226169067],"iteration":375,"passed_time":0.1326191164,"remaining_time":0.2200912996},
{"learn":[4.225963861],"iteration":376,"passed_time":0.1328300734,"remaining_time":0.2195043387},
{"learn":[4.224346548],"iteration":377,"passed_time":0.1330341553,"remaining_time":0.2189080546},
{"learn":[4.222595381],"iteration":378,"passed_time":0.1332540705,"remaining_time":0.2183397831},
{"learn":[4.219700938],"iteration":379,"passed_time":0.1335563185,"remaining_time":0.2179076776},
{"learn":[4.216356207],"iteration":380,"passed_time":0.1338514416,"remaining_time":0.217464678},
{"learn":[4.214326494],"iteration":381,"passed_time":0.134142273,"remaining_time":0.2170155097},
{"learn":[4.212901398],"iteration":382,"passed_time":0.1344053545,"remaining_time":0.2165224641},
{"learn":[4.211331091],"iteration":383,"passed_time":0.1346390613,"remaining_time":0.2159834942},
{"learn":[4.208624791],"iteration":384,"passed_time":0.1348263517,"remaining_time":0.2153719645},
{"learn":[4.204659106],"iteration":385,"passed_time":0.1350277671,"remaining_time":0.214785101},
{"learn":[4.202968852],"iteration":386,"passed_time":0.1352532239,"remaining_time":0.2142383107},
{"learn":[4.197261935],"iteration":387,"passed_time":0.1354506809,"remaining_time":0.2136490122},
{"learn":[4.196934403],"iteration":388,"passed_time":0.1356468046,"remaining_time":0.213059634},
{"learn":[4.192479929],"iteration":389,"passed_time":0.1358994696,"remaining_time":0.2125607088},
{"learn":[4.190243116],"iteration":390,"passed_time":0.1361065515,"remaining_time":0.2119920457},
{"learn":[4.185852431],"iteration":391,"passed_time":0.1363588832,"remaining_time":0.2114954107},
{"learn":[4.180967944],"iteration":392,"passed_time":0.1366470479,"remaining_time":0.2110553641},
{"learn":[4.178283162],"iteration":393,"passed_time":0.1368941296,"remaining_time":0.2105528999},
{"learn":[4.176341157],"iteration":394,"passed_time":0.1370762534,"remaining_time":0.2099522362},
{"learn":[4.176041504],"iteration":395,"passed_time":0.1372487939,"remaining_time":0.2093390695},
{"learn":[4.175564513],"iteration":396,"passed_time":0.137433626,"remaining_time":0.2087467922},
{"learn":[4.170830274],"iteration":397,"passed_time":0.1376895827,"remaining_time":0.2082641426},
{"learn":[4.167804808],"iteration":398,"passed_time":0.1378817897,"remaining_time":0.2076866056},
{"learn":[4.165860548],"iteration":399,"passed_time":0.1381177465,"remaining_time":0.2071766197},
{"learn":[4.160950571],"iteration":400,"passed_time":0.1383815364,"remaining_time":0.2067095768},
{"learn":[4.158544115],"iteration":401,"passed_time":0.138694576,"remaining_time":0.206316807},
{"learn":[4.154448767],"iteration":402,"passed_time":0.1389146162,"remaining_time":0.2057866646},
{"learn":[4.15197457],"iteration":403,"passed_time":0.1391892393,"remaining_time":0.2053385808},
{"learn":[4.149562679],"iteration":404,"passed_time":0.1394150295,"remaining_time":0.2048196112},
{"learn":[4.149327961],"iteration":405,"passed_time":0.1396033616,"remaining_time":0.2042472827},
{"learn":[4.147444889],"iteration":406,"passed_time":0.139784902,"remaining_time":0.2036669457},
{"learn":[4.147254809],"iteration":407,"passed_time":0.1399657758,"remaining_time":0.2030875963},
{"learn":[4.144589165],"iteration":408,"passed_time":0.1401356914,"remaining_time":0.2024943609},
{"learn":[4.141691034],"iteration":409,"passed_time":0.1403784814,"remaining_time":0.2020080586},
{"learn":[4.138893468],"iteration":410,"passed_time":0.1406760628,"remaining_time":0.2016014622},
{"learn":[4.136964597],"iteration":411,"passed_time":0.140885853,"remaining_time":0.2010701009},
{"learn":[4.133773523],"iteration":412,"passed_time":0.1410671018,"remaining_time":0.2004997307},
{"learn":[4.131363444],"iteration":413,"passed_time":0.1412471423,"remaining_time":0.1999295299},
{"learn":[4.130228592],"iteration":414,"passed_time":0.1414951406,"remaining_time":0.1994570055},
{"learn":[4.12884186],"iteration":415,"passed_time":0.1417219308,"remaining_time":0.1989557875},
{"learn":[4.12413494],"iteration":416,"passed_time":0.1419222211,"remaining_time":0.1984188367},
{"learn":[4.119422508],"iteration":417,"passed_time":0.1421353447,"remaining_time":0.1979013651},
{"learn":[4.117038244],"iteration":418,"passed_time":0.1423375934,"remaining_time":0.1973702667},
{"learn":[4.116067631],"iteration":419,"passed_time":0.1425430503,"remaining_time":0.1968451647},
{"learn":[4.110343455],"iteration":420,"passed_time":0.1427657988,"remaining_time":0.1963453623},
{"learn":[4.105604544],"iteration":421,"passed_time":0.1429759224,"remaining_time":0.195829581},
{"learn":[4.103390131],"iteration":422,"passed_time":0.1431948793,"remaining_time":0.195327294},
{"learn":[4.096724402],"iteration":423,"passed_time":0.143392878,"remaining_time":0.194797872},
{"learn":[4.093431279],"iteration":424,"passed_time":0.1435973766,"remaining_time":0.1942788037},
{"learn":[4.091412744],"iteration":425,"passed_time":0.1437995419,"remaining_time":0.1937580683},
{"learn":[4.091192901],"iteration":426,"passed_time":0.1440176238,"remaining_time":0.1932601837},
{"learn":[4.088994581],"iteration":427,"passed_time":0.1442332891,"remaining_time":0.192760377},
{"learn":[4.087845355],"iteration":428,"passed_time":0.1444544543,"remaining_time":0.1922692153},
{"learn":[4.083650279],"iteration":429,"passed_time":0.1446699528,"remaining_time":0.1917717979},
{"learn":[4.079840652],"iteration":430,"passed_time":0.1448797848,"remaining_time":0.1912682077},
{"learn":[4.075707828],"iteration":431,"passed_time":0.1450902834,"remaining_time":0.190766854},
{"learn":[4.071345409],"iteration":432,"passed_time":0.1453600316,"remaining_time":0.1903444293},
{"learn":[4.067460475],"iteration":433,"passed_time":0.1456071966,"remaining_time":0.1898932564},
{"learn":[4.064914749],"iteration":434,"passed_time":0.1458825697,"remaining_time":0.1894796595},
{"learn":[4.063823175],"iteration":435,"passed_time":0.1461679012,"remaining_time":0.1890795786},
{"learn":[4.058898471],"iteration":436,"passed_time":0.1464622325,"remaining_time":0.1886916177},
{"learn":[4.054120355],"iteration":437,"passed_time":0.1467261475,"remaining_time":0.1882650568},
{"learn":[4.052715901],"iteration":438,"passed_time":0.1469246045,"remaining_time":0.1877555879},
{"learn":[4.052114167],"iteration":439,"passed_time":0.147142103,"remaining_time":0.1872717675},
{"learn":[4.051377267],"iteration":440,"passed_time":0.1473358517,"remaining_time":0.1867590501},
{"learn":[4.049275336],"iteration":441,"passed_time":0.1477760155,"remaining_time":0.1865588611},
{"learn":[4.047099198],"iteration":442,"passed_time":0.1480027639,"remaining_time":0.186089254},
{"learn":[4.044348685],"iteration":443,"passed_time":0.1482105959,"remaining_time":0.1855970525},
{"learn":[4.042822379],"iteration":444,"passed_time":0.1484603859,"remaining_time":0.1851584588},
{"learn":[4.041258611],"iteration":445,"passed_time":0.1486955093,"remaining_time":0.1847024937},
{"learn":[4.040044254],"iteration":446,"passed_time":0.1489538826,"remaining_time":0.1842762798},
{"learn":[4.036860137],"iteration":447,"passed_time":0.1492446307,"remaining_time":0.1838907056},
{"learn":[4.036372284],"iteration":448,"passed_time":0.149497504,"remaining_time":0.183459075},
{"learn":[4.03368231],"iteration":449,"passed_time":0.1497547523,"remaining_time":0.1830335861},
{"learn":[4.032439519],"iteration":450,"passed_time":0.1500018756,"remaining_time":0.1825965182},
{"learn":[4.032008634],"iteration":451,"passed_time":0.1502578739,"remaining_time":0.1821710507},
{"learn":[4.030034932],"iteration":452,"passed_time":0.1505349137,"remaining_time":0.1817717391},
{"learn":[4.028173412],"iteration":453,"passed_time":0.1507674955,"remaining_time":0.181319499},
{"learn":[4.023806097],"iteration":454,"passed_time":0.1509576193,"remaining_time":0.1808173681},
{"learn":[4.020239186],"iteration":455,"passed_time":0.1511801178,"remaining_time":0.1803552282},
{"learn":[4.017384838],"iteration":456,"passed_time":0.1514113246,"remaining_time":0.1799044841},
{"learn":[4.016468229],"iteration":457,"passed_time":0.1516476563,"remaining_time":0.1794607636},
{"learn":[4.014530169],"iteration":458,"passed_time":0.1519029463,"remaining_time":0.1790402918},
{"learn":[4.012884822],"iteration":459,"passed_time":0.1521607362,"remaining_time":0.178623473},
{"learn":[4.008924707],"iteration":460,"passed_time":0.1524439844,"remaining_time":0.1782371097},
{"learn":[4.008286778],"iteration":461,"passed_time":0.1527378157,"remaining_time":0.177863517},
{"learn":[4.006444202],"iteration":462,"passed_time":0.1529709808,"remaining_time":0.1774199065},
{"learn":[4.003284363],"iteration":463,"passed_time":0.153249729,"remaining_time":0.1770298593},
{"learn":[3.999811484],"iteration":464,"passed_time":0.153496394,"remaining_time":0.1766033781},
{"learn":[3.997483319],"iteration":465,"passed_time":0.1538137252,"remaining_time":0.1762586465},
{"learn":[3.99708333],"iteration":466,"passed_time":0.1540699319,"remaining_time":0.1758442691},
{"learn":[3.995860263],"iteration":467,"passed_time":0.1543621382,"remaining_time":0.1754714905},
{"learn":[3.994131111],"iteration":468,"passed_time":0.1546258865,"remaining_time":0.1750668352},
{"learn":[3.993125499],"iteration":469,"passed_time":0.1548149269,"remaining_time":0.1745785346},
{"learn":[3.992954084],"iteration":470,"passed_time":0.1550296755,"remaining_time":0.1741203786},
{"learn":[3.990635743],"iteration":471,"passed_time":0.155243799,"remaining_time":0.1736625549},
{"learn":[3.986678254],"iteration":472,"passed_time":0.1554614226,"remaining_time":0.1732096611},
{"learn":[3.986393291],"iteration":473,"passed_time":0.1556760462,"remaining_time":0.172754431},
{"learn":[3.986152671],"iteration":474,"passed_time":0.1558748782,"remaining_time":0.1722827601},
{"learn":[3.985596662],"iteration":475,"passed_time":0.1560667936,"remaining_time":0.1718046215},
{"learn":[3.983853457],"iteration":476,"passed_time":0.1562800005,"remaining_time":0.1713510278},
{"learn":[3.983263928],"iteration":477,"passed_time":0.1564893324,"remaining_time":0.1708942082},
{"learn":[3.980067202],"iteration":478,"passed_time":0.1567031226,"remaining_time":0.1704432712},
{"learn":[3.978115407],"iteration":479,"passed_time":0.1569255378,"remaining_time":0.170002666},
{"learn":[3.972661644],"iteration":480,"passed_time":0.1571641196,"remaining_time":0.1695804118},
{"learn":[3.969938254],"iteration":481,"passed_time":0.1573594099,"remaining_time":0.1691123949},
{"learn":[3.968211434],"iteration":482,"passed_time":0.1575816168,"remaining_time":0.1686743186},
{"learn":[3.966113368],"iteration":483,"passed_time":0.1578139486,"remaining_time":0.1682479287},
{"learn":[3.962246044],"iteration":484,"passed_time":0.1580164889,"remaining_time":0.1677907047},
{"learn":[3.961319703],"iteration":485,"passed_time":0.1582116959,"remaining_time":0.1673267731},
{"learn":[3.96078191],"iteration":486,"passed_time":0.1584120279,"remaining_time":0.1668693436},
{"learn":[3.958913633],"iteration":487,"passed_time":0.1586381931,"remaining_time":0.1664400714},
{"learn":[3.957428286],"iteration":488,"passed_time":0.1588364834,"remaining_time":0.1659825011},
{"learn":[3.952641965],"iteration":489,"passed_time":0.1590431071,"remaining_time":0.1655346624},
{"learn":[3.951486786],"iteration":490,"passed_time":0.1592453974,"remaining_time":0.1650833142},
{"learn":[3.94938344],"iteration":491,"passed_time":0.159456771,"remaining_time":0.164642357},
{"learn":[3.947297924],"iteration":492,"passed_time":0.1596539363,"remaining_time":0.1641877195},
{"learn":[3.946284886],"iteration":493,"passed_time":0.1598245602,"remaining_time":0.1637069382},
{"learn":[3.943288204],"iteration":494,"passed_time":0.1599978924,"remaining_time":0.163230173},
{"learn":[3.943076488],"iteration":495,"passed_time":0.1601725579,"remaining_time":0.1627559862},
{"learn":[3.942347078],"iteration":496,"passed_time":0.1603716815,"remaining_time":0.1623077582},
{"learn":[3.940251541],"iteration":497,"passed_time":0.1605857634,"remaining_time":0.1618756089},
{"learn":[3.939011019],"iteration":498,"passed_time":0.1608451367,"remaining_time":0.1614898066},
{"learn":[3.938760512],"iteration":499,"passed_time":0.1611383848,"remaining_time":0.1611383848},
{"learn":[3.934522727],"iteration":500,"passed_time":0.1614222162,"remaining_time":0.1607778161},
{"learn":[3.930091193],"iteration":501,"passed_time":0.1616301732,"remaining_time":0.1603422833},
{"learn":[3.927671752],"iteration":502,"passed_time":0.1618364634,"remaining_time":0.1599060086},
{"learn":[3.927280041],"iteration":503,"passed_time":0.1620556287,"remaining_time":0.1594833171},
{"learn":[3.925987561],"iteration":504,"passed_time":0.1622540023,"remaining_time":0.1590410518},
{"learn":[3.921645957],"iteration":505,"passed_time":0.1624623759,"remaining_time":0.1586095133},
{"learn":[3.920333743],"iteration":506,"passed_time":0.1626796245,"remaining_time":0.158187485},
{"learn":[3.918659461],"iteration":507,"passed_time":0.1628839565,"remaining_time":0.1577537531},
{"learn":[3.916124385],"iteration":508,"passed_time":0.1631009967,"remaining_time":0.1573331815},
{"learn":[3.913849268],"iteration":509,"passed_time":0.1632890371,"remaining_time":0.1568855455},
{"learn":[3.912826119],"iteration":510,"passed_time":0.1635161189,"remaining_time":0.156476286},
{"learn":[3.910034145],"iteration":511,"passed_time":0.1637379924,"remaining_time":0.156062774},
{"learn":[3.90792379],"iteration":512,"passed_time":0.1639596576,"remaining_time":0.1556498114},
{"learn":[3.907823851],"iteration":513,"passed_time":0.1641744895,"remaining_time":0.1552311321},
{"learn":[3.904527401],"iteration":514,"passed_time":0.1643614466,"remaining_time":0.1547869934},
{"learn":[3.903378283],"iteration":515,"passed_time":0.1645744869,"remaining_time":0.1543683171},
{"learn":[3.902170135],"iteration":516,"passed_time":0.1647771105,"remaining_time":0.1539407048},
{"learn":[3.899435429],"iteration":517,"passed_time":0.1650121923,"remaining_time":0.1535441635},
{"learn":[3.897497505],"iteration":518,"passed_time":0.1652108993,"remaining_time":0.1531145329},
{"learn":[3.896426119],"iteration":519,"passed_time":0.1654208146,"remaining_time":0.1526961365},
{"learn":[3.896044669],"iteration":520,"passed_time":0.1656311882,"remaining_time":0.1522789619},
{"learn":[3.892795942],"iteration":521,"passed_time":0.1658062703,"remaining_time":0.1518302629},
{"learn":[3.892413888],"iteration":522,"passed_time":0.1660033107,"remaining_time":0.1514026371},
{"learn":[3.891738985],"iteration":523,"passed_time":0.1662161426,"remaining_time":0.1509902364},
{"learn":[3.88822057],"iteration":524,"passed_time":0.1664091413,"remaining_time":0.1505606517},
{"learn":[3.883837053],"iteration":525,"passed_time":0.1665967651,"remaining_time":0.1501271229},
{"learn":[3.881769742],"iteration":526,"passed_time":0.1667796805,"remaining_time":0.1496903015},
{"learn":[3.880356898],"iteration":527,"passed_time":0.1669815542,"remaining_time":0.1492713893},
{"learn":[3.879250273],"iteration":528,"passed_time":0.1671821362,"remaining_time":0.1488521477},
{"learn":[3.877174493],"iteration":529,"passed_time":0.1673860515,"remaining_time":0.1484366872},
{"learn":[3.875854201],"iteration":530,"passed_time":0.1675726336,"remaining_time":0.148006714},
{"learn":[3.873189396],"iteration":531,"passed_time":0.1678011737,"remaining_time":0.1476145663},
{"learn":[3.871583368],"iteration":532,"passed_time":0.1680118806,"remaining_time":0.1472074076},
{"learn":[3.869622679],"iteration":533,"passed_time":0.1682303375,"remaining_time":0.1468077477},
{"learn":[3.866860164],"iteration":534,"passed_time":0.1684448361,"remaining_time":0.1464053248},
{"learn":[3.864498444],"iteration":535,"passed_time":0.168654168,"remaining_time":0.1459991305},
{"learn":[3.861416322],"iteration":536,"passed_time":0.1688882081,"remaining_time":0.1456149727},
{"learn":[3.860265769],"iteration":537,"passed_time":0.1691062067,"remaining_time":0.1452175976},
{"learn":[3.859328725],"iteration":538,"passed_time":0.1693139136,"remaining_time":0.1448120857},
{"learn":[3.858521278],"iteration":539,"passed_time":0.1695309955,"remaining_time":0.1444152925},
{"learn":[3.85599111],"iteration":540,"passed_time":0.1697326608,"remaining_time":0.1440060838},
{"learn":[3.852379816],"iteration":541,"passed_time":0.1699221179,"remaining_time":0.1435873247},
{"learn":[3.851327537],"iteration":542,"passed_time":0.1701371165,"remaining_time":0.1431909065},
{"learn":[3.847854898],"iteration":543,"passed_time":0.170360365,"remaining_time":0.1428020707},
{"learn":[3.847083414],"iteration":544,"passed_time":0.1705534054,"remaining_time":0.1423886228},
{"learn":[3.845397429],"iteration":545,"passed_time":0.1707701956,"remaining_time":0.1419957304},
{"learn":[3.841933528],"iteration":546,"passed_time":0.1709640276,"remaining_time":0.141584469},
{"learn":[3.840996474],"iteration":547,"passed_time":0.1711714846,"remaining_time":0.1411852391},
{"learn":[3.838355966],"iteration":548,"passed_time":0.1713986081,"remaining_time":0.1408028638},
{"learn":[3.83342799],"iteration":549,"passed_time":0.1716098567,"remaining_time":0.1404080645},
{"learn":[3.828161535],"iteration":550,"passed_time":0.1718186053,"remaining_time":0.1400118943},
{"learn":[3.823502399],"iteration":551,"passed_time":0.1720493121,"remaining_time":0.1396342243},
{"learn":[3.820068862],"iteration":552,"passed_time":0.172266769,"remaining_time":0.1392463756},
{"learn":[3.817951642],"iteration":553,"passed_time":0.1724881841,"remaining_time":0.1388623288},
{"learn":[3.815785958],"iteration":554,"passed_time":0.1727918488,"remaining_time":0.1385448157},
{"learn":[3.81503012],"iteration":555,"passed_time":0.1729998891,"remaining_time":0.1381509906},
{"learn":[3.813529315],"iteration":556,"passed_time":0.1732015961,"remaining_time":0.1377527954},
{"learn":[3.808881326],"iteration":557,"passed_time":0.173412678,"remaining_time":0.1373627306},
{"learn":[3.808740434],"iteration":558,"passed_time":0.1736186349,"remaining_time":0.136969263},
{"learn":[3.80714352],"iteration":559,"passed_time":0.1738280502,"remaining_time":0.1365791823},
{"learn":[3.80573346],"iteration":560,"passed_time":0.174012299,"remaining_time":0.1361700522},
{"learn":[3.803370052],"iteration":561,"passed_time":0.1741878812,"remaining_time":0.1357549679},
{"learn":[3.803215211],"iteration":562,"passed_time":0.1743817965,"remaining_time":0.1353549646},
{"learn":[3.801309667],"iteration":563,"passed_time":0.1745947951,"remaining_time":0.1349704444},
{"learn":[3.800003847],"iteration":564,"passed_time":0.174806377,"remaining_time":0.1345854407},
{"learn":[3.798026138],"iteration":565,"passed_time":0.1749999174,"remaining_time":0.1341872158},
{"learn":[3.794745847],"iteration":566,"passed_time":0.1751987494,"remaining_time":0.133793754},
{"learn":[3.794312041],"iteration":567,"passed_time":0.1754008731,"remaining_time":0.1334034809},
{"learn":[3.792205926],"iteration":568,"passed_time":0.1756009134,"remaining_time":0.1330122912},
{"learn":[3.788991061],"iteration":569,"passed_time":0.1758004954,"remaining_time":0.1326214264},
{"learn":[3.787391572],"iteration":570,"passed_time":0.1760441188,"remaining_time":0.1322643204},
{"learn":[3.7826445],"iteration":571,"passed_time":0.1762544091,"remaining_time":0.1318826697},
{"learn":[3.781700331],"iteration":572,"passed_time":0.1764810742,"remaining_time":0.1315138197},
{"learn":[3.780045374],"iteration":573,"passed_time":0.1766816562,"remaining_time":0.1311261072},
{"learn":[3.775462644],"iteration":574,"passed_time":0.1769140713,"remaining_time":0.1307625745},
{"learn":[3.773711943],"iteration":575,"passed_time":0.1771303199,"remaining_time":0.1303875966},
{"learn":[3.772415806],"iteration":576,"passed_time":0.1773507351,"remaining_time":0.1300162235},
{"learn":[3.770170875],"iteration":577,"passed_time":0.1775642337,"remaining_time":0.1296403228},
{"learn":[3.765166479],"iteration":578,"passed_time":0.1777760239,"remaining_time":0.1292637411},
{"learn":[3.763976102],"iteration":579,"passed_time":0.1780006891,"remaining_time":0.1288970507},
{"learn":[3.760761708],"iteration":580,"passed_time":0.1782879372,"remaining_time":0.1285759822},
{"learn":[3.758155662],"iteration":581,"passed_time":0.1784921441,"remaining_time":0.1281953888},
{"learn":[3.756844548],"iteration":582,"passed_time":0.1787042261,"remaining_time":0.1278210331},
{"learn":[3.753098923],"iteration":583,"passed_time":0.1789436411,"remaining_time":0.1274667033},
{"learn":[3.751618946],"iteration":584,"passed_time":0.1791488481,"remaining_time":0.1270884991},
{"learn":[3.751398464],"iteration":585,"passed_time":0.1793446385,"remaining_time":0.1267042326},
{"learn":[3.749920103],"iteration":586,"passed_time":0.1795723453,"remaining_time":0.1263430641},
{"learn":[3.748237465],"iteration":587,"passed_time":0.1797690106,"remaining_time":0.1259605993},
{"learn":[3.746021536],"iteration":588,"passed_time":0.1799902592,"remaining_time":0.1255959194},
{"learn":[3.74417648],"iteration":589,"passed_time":0.180220591,"remaining_time":0.1252380378},
{"learn":[3.738788389],"iteration":590,"passed_time":0.1804354645,"remaining_time":0.12486989},
{"learn":[3.736021611],"iteration":591,"passed_time":0.1806452548,"remaining_time":0.1244987567},
{"learn":[3.734546151],"iteration":592,"passed_time":0.1809465445,"remaining_time":0.1241909673},
{"learn":[3.733527479],"iteration":593,"passed_time":0.1812130427,"remaining_time":0.1238594197},
{"learn":[3.733026392],"iteration":594,"passed_time":0.1814553744,"remaining_time":0.1235116414},
{"learn":[3.730314752],"iteration":595,"passed_time":0.1817251643,"remaining_time":0.1231828295},
{"learn":[3.727342596],"iteration":596,"passed_time":0.1820124124,"remaining_time":0.1228660003},
{"learn":[3.725459604],"iteration":597,"passed_time":0.1822817439,"remaining_time":0.1225372258},
{"learn":[3.723158842],"iteration":598,"passed_time":0.1825328672,"remaining_time":0.1221964604},
{"learn":[3.722362756],"iteration":599,"passed_time":0.1827584907,"remaining_time":0.1218389938},
{"learn":[3.721443615],"iteration":600,"passed_time":0.1829870309,"remaining_time":0.1214839024},
{"learn":[3.720743486],"iteration":601,"passed_time":0.1832157793,"remaining_time":0.1211293691},
{"learn":[3.720215334],"iteration":602,"passed_time":0.1834271946,"remaining_time":0.1207638412},
{"learn":[3.719436563],"iteration":603,"passed_time":0.1837170677,"remaining_time":0.1204502629},
{"learn":[3.715046574],"iteration":604,"passed_time":0.1839984825,"remaining_time":0.1201312406},
{"learn":[3.71443396],"iteration":605,"passed_time":0.1842066061,"remaining_time":0.1197646911},
{"learn":[3.712938941],"iteration":606,"passed_time":0.1844104381,"remaining_time":0.1193958849},
{"learn":[3.712814764],"iteration":607,"passed_time":0.1846868112,"remaining_time":0.1190743914},
{"learn":[3.71235348],"iteration":608,"passed_time":0.1848914348,"remaining_time":0.1187069803},
{"learn":[3.711223749],"iteration":609,"passed_time":0.1850968085,"remaining_time":0.1183405825},
{"learn":[3.710755648],"iteration":610,"passed_time":0.185321182,"remaining_time":0.1179868082},
{"learn":[3.708668039],"iteration":611,"passed_time":0.1855192223,"remaining_time":0.1176167619},
{"learn":[3.705623591],"iteration":612,"passed_time":0.1857648874,"remaining_time":0.1172773432},
{"learn":[3.704045802],"iteration":613,"passed_time":0.1860397189,"remaining_time":0.1169565659},
{"learn":[3.699915209],"iteration":614,"passed_time":0.1863103837,"remaining_time":0.1166333296},
{"learn":[3.696182221],"iteration":615,"passed_time":0.1866582564,"remaining_time":0.1163583936},
{"learn":[3.694263278],"iteration":616,"passed_time":0.1868633384,"remaining_time":0.1159945844},
{"learn":[3.693810229],"iteration":617,"passed_time":0.1870710037,"remaining_time":0.1156328858},
{"learn":[3.690900932],"iteration":618,"passed_time":0.1872615024,"remaining_time":0.1152611186},
{"learn":[3.688020895],"iteration":619,"passed_time":0.1874578761,"remaining_time":0.114893537},
{"learn":[3.685491894],"iteration":620,"passed_time":0.1876394582,"remaining_time":0.1145174793},
{"learn":[3.684328128],"iteration":621,"passed_time":0.1878289569,"remaining_time":0.1141468581},
{"learn":[3.680640153],"iteration":622,"passed_time":0.1880357472,"remaining_time":0.113787282},
{"learn":[3.678932783],"iteration":623,"passed_time":0.1882461625,"remaining_time":0.11343038},
{"learn":[3.674167041],"iteration":624,"passed_time":0.1884532028,"remaining_time":0.1130719217},
{"learn":[3.672200976],"iteration":625,"passed_time":0.1886591597,"remaining_time":0.1127132999},
{"learn":[3.670606604],"iteration":626,"passed_time":0.1888574084,"remaining_time":0.1123505795},
{"learn":[3.665506042],"iteration":627,"passed_time":0.1890506155,"remaining_time":0.1119853964},
{"learn":[3.664214007],"iteration":628,"passed_time":0.1892606141,"remaining_time":0.1116306643},
{"learn":[3.66261643],"iteration":629,"passed_time":0.1894603627,"remaining_time":0.1112703718},
{"learn":[3.662118449],"iteration":630,"passed_time":0.1896499865,"remaining_time":0.1109046672},
{"learn":[3.660871366],"iteration":631,"passed_time":0.1898454852,"remaining_time":0.1105429407},
{"learn":[3.656695243],"iteration":632,"passed_time":0.1900507338,"remaining_time":0.1101873923},
{"learn":[3.654497801],"iteration":633,"passed_time":0.1902481492,"remaining_time":0.1098277959},
{"learn":[3.654189134],"iteration":634,"passed_time":0.190478981,"remaining_time":0.1094879182},
{"learn":[3.653957699],"iteration":635,"passed_time":0.1906564798,"remaining_time":0.1091178595},
{"learn":[3.651920725],"iteration":636,"passed_time":0.1908525201,"remaining_time":0.1087589714},
{"learn":[3.65106705],"iteration":637,"passed_time":0.1910793936,"remaining_time":0.1084180885},
{"learn":[3.650612844],"iteration":638,"passed_time":0.1912733923,"remaining_time":0.10805899},
{"learn":[3.649884732],"iteration":639,"passed_time":0.1914528078,"remaining_time":0.1076922044},
{"learn":[3.646276182],"iteration":640,"passed_time":0.1916626814,"remaining_time":0.1073430618},
{"learn":[3.645808194],"iteration":641,"passed_time":0.1918679717,"remaining_time":0.1069917973},
{"learn":[3.645042989],"iteration":642,"passed_time":0.1922310943,"remaining_time":0.1067286169},
{"learn":[3.639864499],"iteration":643,"passed_time":0.1924364679,"remaining_time":0.1063779233},
{"learn":[3.637318478],"iteration":644,"passed_time":0.1926256333,"remaining_time":0.1060187594},
{"learn":[3.636344905],"iteration":645,"passed_time":0.1928200904,"remaining_time":0.1056630216},
{"learn":[3.634754643],"iteration":646,"passed_time":0.1930186724,"remaining_time":0.105310033},
{"learn":[3.630724975],"iteration":647,"passed_time":0.1932572541,"remaining_time":0.1049792491},
{"learn":[3.629408252],"iteration":648,"passed_time":0.1934538361,"remaining_time":0.1046260346},
{"learn":[3.62790646],"iteration":649,"passed_time":0.1936705847,"remaining_time":0.104284161},
{"learn":[3.627388973],"iteration":650,"passed_time":0.1938557085,"remaining_time":0.1039257177},
{"learn":[3.625163557],"iteration":651,"passed_time":0.1940464572,"remaining_time":0.1035708084},
{"learn":[3.623701985],"iteration":652,"passed_time":0.1942302476,"remaining_time":0.1032127043},
{"learn":[3.622342639],"iteration":653,"passed_time":0.194530329,"remaining_time":0.1029166572},
{"learn":[3.621130639],"iteration":654,"passed_time":0.1947154111,"remaining_time":0.1025600257},
{"learn":[3.619125665],"iteration":655,"passed_time":0.1949004932,"remaining_time":0.1022039171},
{"learn":[3.618878783],"iteration":656,"passed_time":0.1950775753,"remaining_time":0.1018441527},
{"learn":[3.616207429],"iteration":657,"passed_time":0.1952688657,"remaining_time":0.1014923284},
{"learn":[3.61206486],"iteration":658,"passed_time":0.1954641561,"remaining_time":0.101143061},
{"learn":[3.611955873],"iteration":659,"passed_time":0.1956526965,"remaining_time":0.100790783},
{"learn":[3.610713743],"iteration":660,"passed_time":0.1958370703,"remaining_time":0.1004368636},
{"learn":[3.610044025],"iteration":661,"passed_time":0.1960441522,"remaining_time":0.1000950505},
{"learn":[3.607342669],"iteration":662,"passed_time":0.1962194427,"remaining_time":0.09973748445},
{"learn":[3.602510618],"iteration":663,"passed_time":0.1964178581,"remaining_time":0.09939216913},
{"learn":[3.600492392],"iteration":664,"passed_time":0.1966143567,"remaining_time":0.09904633009},
{"learn":[3.597171065],"iteration":665,"passed_time":0.1968185637,"remaining_time":0.09870480523},
{"learn":[3.594358798],"iteration":666,"passed_time":0.1970025625,"remaining_time":0.09835360316},
{"learn":[3.593945251],"iteration":667,"passed_time":0.1971840613,"remaining_time":0.0980016592},
{"learn":[3.593607748],"iteration":668,"passed_time":0.1975126841,"remaining_time":0.09772301709},
{"learn":[3.592238714],"iteration":669,"passed_time":0.1977093078,"remaining_time":0.0973792113},
{"learn":[3.590144654],"iteration":670,"passed_time":0.1978934316,"remaining_time":0.09702971532},
{"learn":[3.587151536],"iteration":671,"passed_time":0.1981091385,"remaining_time":0.0966961271},
{"learn":[3.586070865],"iteration":672,"passed_time":0.1983136371,"remaining_time":0.09635744328},
{"learn":[3.585102746],"iteration":673,"passed_time":0.1985027192,"remaining_time":0.09601170096},
{"learn":[3.584362847],"iteration":674,"passed_time":0.1986875513,"remaining_time":0.09566437653},
{"learn":[3.581407561],"iteration":675,"passed_time":0.1988845916,"remaining_time":0.09532338415},
{"learn":[3.57919422],"iteration":676,"passed_time":0.1990818403,"remaining_time":0.09498291642},
{"learn":[3.577632204],"iteration":677,"passed_time":0.1992794223,"remaining_time":0.09464302948},
{"learn":[3.573911195],"iteration":678,"passed_time":0.1995066291,"remaining_time":0.09431756694},
{"learn":[3.573408216],"iteration":679,"passed_time":0.1998093355,"remaining_time":0.09402792257},
{"learn":[3.571076482],"iteration":680,"passed_time":0.2000147924,"remaining_time":0.09369268544},
{"learn":[3.568177107],"iteration":681,"passed_time":0.2001988329,"remaining_time":0.09334784289},
{"learn":[3.564824621],"iteration":682,"passed_time":0.2004121231,"remaining_time":0.09301704689},
{"learn":[3.562475026],"iteration":683,"passed_time":0.2006664131,"remaining_time":0.09270553587},
{"learn":[3.561226889],"iteration":684,"passed_time":0.2008751617,"remaining_time":0.09237324954},
{"learn":[3.559383467],"iteration":685,"passed_time":0.2010752437,"remaining_time":0.09203735644},
{"learn":[3.555209766],"iteration":686,"passed_time":0.2012763673,"remaining_time":0.0917023333},
{"learn":[3.55345383],"iteration":687,"passed_time":0.201471741,"remaining_time":0.09136509187},
{"learn":[3.552300968],"iteration":688,"passed_time":0.2016704481,"remaining_time":0.09102976683},
{"learn":[3.551253986],"iteration":689,"passed_time":0.201882655,"remaining_time":0.09070090296},
{"learn":[3.549807725],"iteration":690,"passed_time":0.2021351116,"remaining_time":0.09039037553},
{"learn":[3.547992926],"iteration":691,"passed_time":0.2023424852,"remaining_time":0.09005995008},
{"learn":[3.545438607],"iteration":692,"passed_time":0.2026042335,"remaining_time":0.0897539678},
{"learn":[3.543313763],"iteration":693,"passed_time":0.2028129821,"remaining_time":0.08942474427},
{"learn":[3.542962896],"iteration":694,"passed_time":0.2030099808,"remaining_time":0.089090711},
{"learn":[3.539800465],"iteration":695,"passed_time":0.2031957712,"remaining_time":0.08875217594},
{"learn":[3.53953187],"iteration":696,"passed_time":0.2033653951,"remaining_time":0.08840705124},
{"learn":[3.536332425],"iteration":697,"passed_time":0.2035697271,"remaining_time":0.08807744638},
{"learn":[3.534993327],"iteration":698,"passed_time":0.2037571008,"remaining_time":0.08774089749},
{"learn":[3.531637011],"iteration":699,"passed_time":0.2039495162,"remaining_time":0.08740693552},
{"learn":[3.531040284],"iteration":700,"passed_time":0.2041401399,"remaining_time":0.08707261318},
{"learn":[3.529973872],"iteration":701,"passed_time":0.204326597,"remaining_time":0.0867369315},
{"learn":[3.527325183],"iteration":702,"passed_time":0.2045090958,"remaining_time":0.08640000207},
{"learn":[3.527200815],"iteration":703,"passed_time":0.2046878863,"remaining_time":0.08606195219},
{"learn":[3.523459911],"iteration":704,"passed_time":0.2048645518,"remaining_time":0.08572346493},
{"learn":[3.522729934],"iteration":705,"passed_time":0.205037134,"remaining_time":0.08538373567},
{"learn":[3.522260582],"iteration":706,"passed_time":0.2052271327,"remaining_time":0.08505169714},
{"learn":[3.518641591],"iteration":707,"passed_time":0.2054247564,"remaining_time":0.08472320461},
{"learn":[3.516856405],"iteration":708,"passed_time":0.2056150051,"remaining_time":0.08439205428},
{"learn":[3.515083413],"iteration":709,"passed_time":0.2058265037,"remaining_time":0.08406998038},
{"learn":[3.514671214],"iteration":710,"passed_time":0.206032419,"remaining_time":0.08374594809},
{"learn":[3.512617621],"iteration":711,"passed_time":0.2062190428,"remaining_time":0.08341444426},
{"learn":[3.510747971],"iteration":712,"passed_time":0.2064219997,"remaining_time":0.08308992135},
{"learn":[3.508149266],"iteration":713,"passed_time":0.20663929,"remaining_time":0.08277148029},
{"learn":[3.504557165],"iteration":714,"passed_time":0.2068314137,"remaining_time":0.08244329076},
{"learn":[3.501367208],"iteration":715,"passed_time":0.2070507455,"remaining_time":0.08212627337},
{"learn":[3.497593362],"iteration":716,"passed_time":0.2072449109,"remaining_time":0.08179959524},
{"learn":[3.496291169],"iteration":717,"passed_time":0.2074659928,"remaining_time":0.08148385789},
{"learn":[3.49330374],"iteration":718,"passed_time":0.2077616158,"remaining_time":0.08119751605},
{"learn":[3.490044385],"iteration":719,"passed_time":0.2080690721,"remaining_time":0.08091575026},
{"learn":[3.488891789],"iteration":720,"passed_time":0.2082613625,"remaining_time":0.08058934831},
{"learn":[3.486869081],"iteration":721,"passed_time":0.2084855693,"remaining_time":0.08027560702},
{"learn":[3.486303638],"iteration":722,"passed_time":0.2086613598,"remaining_time":0.07994356386},
{"learn":[3.486035862],"iteration":723,"passed_time":0.2088707751,"remaining_time":0.07962477061},
{"learn":[3.482668951],"iteration":724,"passed_time":0.2090646488,"remaining_time":0.07930038403},
{"learn":[3.47820549],"iteration":725,"passed_time":0.2092583975,"remaining_time":0.0789763098},
{"learn":[3.474392283],"iteration":726,"passed_time":0.209484896,"remaining_time":0.07866489217},
{"learn":[3.472268163],"iteration":727,"passed_time":0.2097128111,"remaining_time":0.07835423713},
{"learn":[3.471209164],"iteration":728,"passed_time":0.2099068515,"remaining_time":0.07803121641},
{"learn":[3.470049971],"iteration":729,"passed_time":0.2100849337,"remaining_time":0.0777026467},
{"learn":[3.469078654],"iteration":730,"passed_time":0.2102857657,"remaining_time":0.07738286041},
{"learn":[3.468643292],"iteration":731,"passed_time":0.2105103892,"remaining_time":0.07707210969},
{"learn":[3.468134848],"iteration":732,"passed_time":0.2107068045,"remaining_time":0.07675131897},
{"learn":[3.467820182],"iteration":733,"passed_time":0.2109203864,"remaining_time":0.07643708827},
{"learn":[3.465776156],"iteration":734,"passed_time":0.2111627181,"remaining_time":0.07613349702},
{"learn":[3.463037608],"iteration":735,"passed_time":0.2113378836,"remaining_time":0.07580598},
{"learn":[3.45965637],"iteration":736,"passed_time":0.2115110492,"remaining_time":0.07547816273},
{"learn":[3.457275091],"iteration":737,"passed_time":0.2116965896,"remaining_time":0.07515515782},
{"learn":[3.455522955],"iteration":738,"passed_time":0.21188788,"remaining_time":0.07483455572},
{"learn":[3.451270508],"iteration":739,"passed_time":0.2120757537,"remaining_time":0.07451310266},
{"learn":[3.450978947],"iteration":740,"passed_time":0.2122910023,"remaining_time":0.0742015784},
{"learn":[3.450608492],"iteration":741,"passed_time":0.2125277091,"remaining_time":0.07389777485},
{"learn":[3.448122004],"iteration":742,"passed_time":0.2127140828,"remaining_time":0.07357674197},
{"learn":[3.445646714],"iteration":743,"passed_time":0.2129208314,"remaining_time":0.07326308178},
{"learn":[3.44411263],"iteration":744,"passed_time":0.2131109552,"remaining_time":0.07294401821},
{"learn":[3.443264164],"iteration":745,"passed_time":0.2133038706,"remaining_time":0.07262625083},
{"learn":[3.439521363],"iteration":746,"passed_time":0.2134961193,"remaining_time":0.07230859193},
{"learn":[3.436809225],"iteration":747,"passed_time":0.2137191178,"remaining_time":0.07200162792},
{"learn":[3.435509465],"iteration":748,"passed_time":0.2139572412,"remaining_time":0.07169995666},
{"learn":[3.434450277],"iteration":749,"passed_time":0.2141792397,"remaining_time":0.07139307991},
{"learn":[3.431786753],"iteration":750,"passed_time":0.2144019466,"remaining_time":0.07108666404},
{"learn":[3.430150302],"iteration":751,"passed_time":0.214644195,"remaining_time":0.07078691536},
{"learn":[3.42696281],"iteration":752,"passed_time":0.2148304437,"remaining_time":0.07046895033},
{"learn":[3.426870334],"iteration":753,"passed_time":0.2150536506,"remaining_time":0.07016339262},
{"learn":[3.425200309],"iteration":754,"passed_time":0.2153276071,"remaining_time":0.0698745215},
{"learn":[3.423383783],"iteration":755,"passed_time":0.2155628555,"remaining_time":0.06957319675},
{"learn":[3.422752979],"iteration":756,"passed_time":0.2158191455,"remaining_time":0.06927880099},
{"learn":[3.420845924],"iteration":757,"passed_time":0.2160653938,"remaining_time":0.06898129987},
{"learn":[3.418917862],"iteration":758,"passed_time":0.2162614342,"remaining_time":0.06866799162},
{"learn":[3.417095735],"iteration":759,"passed_time":0.2164534329,"remaining_time":0.06835371565},
{"learn":[3.414391848],"iteration":760,"passed_time":0.2167040146,"remaining_time":0.06805815963},
{"learn":[3.41426711],"iteration":761,"passed_time":0.2169526379,"remaining_time":0.06776211},
{"learn":[3.411976013],"iteration":762,"passed_time":0.2172158862,"remaining_time":0.06747072742},
{"learn":[3.408614844],"iteration":763,"passed_time":0.217543259,"remaining_time":0.06719922659},
{"learn":[3.407906721],"iteration":764,"passed_time":0.2178021739,"remaining_time":0.06690655016},
{"learn":[3.407494015],"iteration":765,"passed_time":0.2180452973,"remaining_time":0.06660913782},
{"learn":[3.406287128],"iteration":766,"passed_time":0.2182263378,"remaining_time":0.06629300743},
{"learn":[3.404600442],"iteration":767,"passed_time":0.2184160032,"remaining_time":0.06597983429},
{"learn":[3.404012662],"iteration":768,"passed_time":0.2186129602,"remaining_time":0.06566917269},
{"learn":[3.400398762],"iteration":769,"passed_time":0.2188140422,"remaining_time":0.06536003857},
{"learn":[3.399737714],"iteration":770,"passed_time":0.2189970826,"remaining_time":0.0650458261},
{"learn":[3.399185251],"iteration":771,"passed_time":0.2191719981,"remaining_time":0.06472955385},
{"learn":[3.397245411],"iteration":772,"passed_time":0.219389705,"remaining_time":0.0644262135},
{"learn":[3.396229831],"iteration":773,"passed_time":0.2195914953,"remaining_time":0.06411844696},
{"learn":[3.394002836],"iteration":774,"passed_time":0.2197854107,"remaining_time":0.06380866762},
{"learn":[3.389617243],"iteration":775,"passed_time":0.2200000759,"remaining_time":0.06350517656},
{"learn":[3.385426488],"iteration":776,"passed_time":0.2202056579,"remaining_time":0.06319930722},
{"learn":[3.385072258],"iteration":777,"passed_time":0.2204084482,"remaining_time":0.06289289911},
{"learn":[3.383842366],"iteration":778,"passed_time":0.2206131135,"remaining_time":0.06258728894},
{"learn":[3.380110746],"iteration":779,"passed_time":0.2208236121,"remaining_time":0.0622835829},
{"learn":[3.378595218],"iteration":780,"passed_time":0.2210049026,"remaining_time":0.06197192531},
{"learn":[3.377371219],"iteration":781,"passed_time":0.2211991929,"remaining_time":0.06166422514},
{"learn":[3.375814782],"iteration":782,"passed_time":0.221393525,"remaining_time":0.06135682621},
{"learn":[3.374195887],"iteration":783,"passed_time":0.2215833987,"remaining_time":0.0610484874},
{"learn":[3.373704309],"iteration":784,"passed_time":0.2217731891,"remaining_time":0.06074042759},
{"learn":[3.372971757],"iteration":785,"passed_time":0.2219609379,"remaining_time":0.06043211286},
{"learn":[3.371565136],"iteration":786,"passed_time":0.2221606032,"remaining_time":0.06012732971},
{"learn":[3.3700309],"iteration":787,"passed_time":0.2223869767,"remaining_time":0.05982999881},
{"learn":[3.368186663],"iteration":788,"passed_time":0.222598767,"remaining_time":0.05952894782},
{"learn":[3.366710398],"iteration":789,"passed_time":0.2228025989,"remaining_time":0.05922600731},
{"learn":[3.364598042],"iteration":790,"passed_time":0.2230302641,"remaining_time":0.05892961466},
{"learn":[3.36348442],"iteration":791,"passed_time":0.2232197628,"remaining_time":0.05862337205},
{"learn":[3.362001759],"iteration":792,"passed_time":0.2234199282,"remaining_time":0.05832020823},
{"learn":[3.361580401],"iteration":793,"passed_time":0.2235952603,"remaining_time":0.05801086099},
{"learn":[3.359543675],"iteration":794,"passed_time":0.2237717175,"remaining_time":0.05770214098},
{"learn":[3.35766119],"iteration":795,"passed_time":0.2239773411,"remaining_time":0.05740122812},
{"learn":[3.354592969],"iteration":796,"passed_time":0.2241655899,"remaining_time":0.05709612891},
{"learn":[3.350985986],"iteration":797,"passed_time":0.2243705052,"remaining_time":0.0567955414},
{"learn":[3.349589624],"iteration":798,"passed_time":0.2245937537,"remaining_time":0.05649980537},
{"learn":[3.349110856],"iteration":799,"passed_time":0.224786919,"remaining_time":0.05619672976},
{"learn":[3.345315441],"iteration":800,"passed_time":0.2250129592,"remaining_time":0.05590209598},
{"learn":[3.34397474],"iteration":801,"passed_time":0.2252649575,"remaining_time":0.05561404188},
{"learn":[3.343800902],"iteration":802,"passed_time":0.2254666645,"remaining_time":0.05531373961},
{"learn":[3.342329465],"iteration":803,"passed_time":0.2256437883,"remaining_time":0.05500768969},
{"learn":[3.34220347],"iteration":804,"passed_time":0.2258348704,"remaining_time":0.05470534128},
{"learn":[3.341279219],"iteration":805,"passed_time":0.2260179525,"remaining_time":0.05440134341},
{"learn":[3.337329521],"iteration":806,"passed_time":0.2262229928,"remaining_time":0.05410289667},
{"learn":[3.336708453],"iteration":807,"passed_time":0.2264118666,"remaining_time":0.05380083958},
{"learn":[3.333252703],"iteration":808,"passed_time":0.2266019486,"remaining_time":0.05349934757},
{"learn":[3.332186769],"iteration":809,"passed_time":0.2268004473,"remaining_time":0.05320010492},
{"learn":[3.330594851],"iteration":810,"passed_time":0.2270642372,"remaining_time":0.05291632655},
{"learn":[3.327867442],"iteration":811,"passed_time":0.2272884857,"remaining_time":0.0526234425},
{"learn":[3.327563111],"iteration":812,"passed_time":0.227489151,"remaining_time":0.05232530288},
{"learn":[3.326308994],"iteration":813,"passed_time":0.2277118162,"remaining_time":0.05203242975},
{"learn":[3.326249879],"iteration":814,"passed_time":0.2279065233,"remaining_time":0.05173338258},
{"learn":[3.322336238],"iteration":815,"passed_time":0.2281159385,"remaining_time":0.05143790771},
{"learn":[3.320491154],"iteration":816,"passed_time":0.2283205622,"remaining_time":0.05114157023},
{"learn":[3.320434271],"iteration":817,"passed_time":0.2285230608,"remaining_time":0.05084498419},
{"learn":[3.319609638],"iteration":818,"passed_time":0.2287213512,"remaining_time":0.05054769788},
{"learn":[3.316182682],"iteration":819,"passed_time":0.2289071416,"remaining_time":0.05024790913},
{"learn":[3.313126612],"iteration":820,"passed_time":0.2291010986,"remaining_time":0.04995017863},
{"learn":[3.311222803],"iteration":821,"passed_time":0.2293107639,"remaining_time":0.04965610216},
{"learn":[3.309627335],"iteration":822,"passed_time":0.2295461373,"remaining_time":0.04936775979},
{"learn":[3.307974895],"iteration":823,"passed_time":0.2298874267,"remaining_time":0.04910216882},
{"learn":[3.307321505],"iteration":824,"passed_time":0.2300783005,"remaining_time":0.04880448798},
{"learn":[3.306759087],"iteration":825,"passed_time":0.2302555493,"remaining_time":0.04850419561},
{"learn":[3.30484037],"iteration":826,"passed_time":0.2304767978,"remaining_time":0.0482134051},
{"learn":[3.30201994],"iteration":827,"passed_time":0.2306904214,"remaining_time":0.04792119864},
{"learn":[3.299302297],"iteration":828,"passed_time":0.2309492113,"remaining_time":0.04763849835},
{"learn":[3.298132671],"iteration":829,"passed_time":0.231201918,"remaining_time":0.04735460971},
{"learn":[3.296976183],"iteration":830,"passed_time":0.2314730828,"remaining_time":0.04707454994},
{"learn":[3.293144745],"iteration":831,"passed_time":0.2317188729,"remaining_time":0.04678938779},
{"learn":[3.290284404],"iteration":832,"passed_time":0.2319533713,"remaining_time":0.04650205643},
{"learn":[3.288285745],"iteration":833,"passed_time":0.232152495,"remaining_time":0.04620781075},
{"learn":[3.286662667],"iteration":834,"passed_time":0.2323702435,"remaining_time":0.04591747327},
{"learn":[3.285692682],"iteration":835,"passed_time":0.2325821171,"remaining_time":0.04562615695},
{"learn":[3.284565611],"iteration":836,"passed_time":0.2328198239,"remaining_time":0.04534006128},
{"learn":[3.283897383],"iteration":837,"passed_time":0.2330299891,"remaining_time":0.04504875685},
{"learn":[3.280712855],"iteration":838,"passed_time":0.2332527793,"remaining_time":0.0447600685},
{"learn":[3.280468341],"iteration":839,"passed_time":0.233441903,"remaining_time":0.04446512439},
{"learn":[3.277814895],"iteration":840,"passed_time":0.2336379851,"remaining_time":0.04417174748},
{"learn":[3.276316385],"iteration":841,"passed_time":0.2338414837,"remaining_time":0.04387999338},
{"learn":[3.27557063],"iteration":842,"passed_time":0.234043399,"remaining_time":0.0435881538},
{"learn":[3.27499628],"iteration":843,"passed_time":0.2342745225,"remaining_time":0.04330192596},
{"learn":[3.273569958],"iteration":844,"passed_time":0.2344782711,"remaining_time":0.04301080713},
{"learn":[3.269665595],"iteration":845,"passed_time":0.2346773115,"remaining_time":0.04271903779},
{"learn":[3.267984685],"iteration":846,"passed_time":0.2349166432,"remaining_time":0.04243476554},
{"learn":[3.267702508],"iteration":847,"passed_time":0.2351207669,"remaining_time":0.0421442884},
{"learn":[3.266671924],"iteration":848,"passed_time":0.2353078073,"remaining_time":0.04185097633},
{"learn":[3.265359825],"iteration":849,"passed_time":0.2355154309,"remaining_time":0.04156154663},
{"learn":[3.2618983],"iteration":850,"passed_time":0.2357200962,"remaining_time":0.04127179123},
{"learn":[3.260456253],"iteration":851,"passed_time":0.2359032617,"remaining_time":0.04097850085},
{"learn":[3.258389147],"iteration":852,"passed_time":0.2361280935,"remaining_time":0.04069264917},
{"learn":[3.258108469],"iteration":853,"passed_time":0.2363277172,"remaining_time":0.0404026308},
{"learn":[3.256424936],"iteration":854,"passed_time":0.2365443824,"remaining_time":0.04011571397},
{"learn":[3.254817983],"iteration":855,"passed_time":0.2367364228,"remaining_time":0.03982481878},
{"learn":[3.253898449],"iteration":856,"passed_time":0.2369504213,"remaining_time":0.03953781826},
{"learn":[3.253023652],"iteration":857,"passed_time":0.2371694199,"remaining_time":0.03925181541},
{"learn":[3.252845542],"iteration":858,"passed_time":0.2373613769,"remaining_time":0.03896152986},
{"learn":[3.252316026],"iteration":859,"passed_time":0.2375510007,"remaining_time":0.03867109313},
{"learn":[3.24975301],"iteration":860,"passed_time":0.2377623326,"remaining_time":0.03838439516},
{"learn":[3.249151075],"iteration":861,"passed_time":0.237958248,"remaining_time":0.03809540397},
{"learn":[3.246257135],"iteration":862,"passed_time":0.2381418301,"remaining_time":0.03780467059},
{"learn":[3.243826471],"iteration":863,"passed_time":0.2384351198,"remaining_time":0.03753145404},
{"learn":[3.243190653],"iteration":864,"passed_time":0.2387133263,"remaining_time":0.03725583705},
{"learn":[3.24008797],"iteration":865,"passed_time":0.2389518247,"remaining_time":0.03697406987},
{"learn":[3.240036811],"iteration":866,"passed_time":0.2392194062,"remaining_time":0.03669686393},
{"learn":[3.238676314],"iteration":867,"passed_time":0.2394210299,"remaining_time":0.03640964971},
{"learn":[3.237848782],"iteration":868,"passed_time":0.2396246535,"remaining_time":0.03612293396},
{"learn":[3.236405498],"iteration":869,"passed_time":0.2398055273,"remaining_time":0.03583300983},
{"learn":[3.233378068],"iteration":870,"passed_time":0.2400084426,"remaining_time":0.03554660057},
{"learn":[3.233169169],"iteration":871,"passed_time":0.2402132329,"remaining_time":0.03526065805},
{"learn":[3.232434885],"iteration":872,"passed_time":0.2404523563,"remaining_time":0.03497989605},
{"learn":[3.229978115],"iteration":873,"passed_time":0.2406535633,"remaining_time":0.03469376314},
{"learn":[3.229648848],"iteration":874,"passed_time":0.2408467704,"remaining_time":0.03440668148},
{"learn":[3.227208761],"iteration":875,"passed_time":0.2410332275,"remaining_time":0.03411885868},
{"learn":[3.226258869],"iteration":876,"passed_time":0.2412397261,"remaining_time":0.03383407789},
{"learn":[3.225331995],"iteration":877,"passed_time":0.241454433,"remaining_time":0.03355061597},
{"learn":[3.221968268],"iteration":878,"passed_time":0.2422816358,"remaining_time":0.0333516245},
{"learn":[3.221166317],"iteration":879,"passed_time":0.2424720929,"remaining_time":0.0330643763},
{"learn":[3.220047503],"iteration":880,"passed_time":0.2426677166,"remaining_time":0.03277804571},
{"learn":[3.21982781],"iteration":881,"passed_time":0.2428699652,"remaining_time":0.03249280714},
{"learn":[3.216693405],"iteration":882,"passed_time":0.2430770055,"remaining_time":0.03220839145},
{"learn":[3.214798761],"iteration":883,"passed_time":0.2433355455,"remaining_time":0.03193090868},
{"learn":[3.214395085],"iteration":884,"passed_time":0.2435233775,"remaining_time":0.0316442807},
{"learn":[3.213470696],"iteration":885,"passed_time":0.2438375421,"remaining_time":0.0313741307},
{"learn":[3.211595017],"iteration":886,"passed_time":0.2440217076,"remaining_time":0.03108732013},
{"learn":[3.210965255],"iteration":887,"passed_time":0.244208248,"remaining_time":0.03080104029},
{"learn":[3.209413583],"iteration":888,"passed_time":0.2444518714,"remaining_time":0.03052211217},
{"learn":[3.208331683],"iteration":889,"passed_time":0.244657995,"remaining_time":0.03023862859},
{"learn":[3.207110711],"iteration":890,"passed_time":0.2448717852,"remaining_time":0.02995625655},
{"learn":[3.204519413],"iteration":891,"passed_time":0.2451375751,"remaining_time":0.02968033421},
{"learn":[3.201421296],"iteration":892,"passed_time":0.2453364071,"remaining_time":0.02939641161},
{"learn":[3.200691259],"iteration":893,"passed_time":0.2455433224,"remaining_time":0.02911363778},
{"learn":[3.200485067],"iteration":894,"passed_time":0.2457439044,"remaining_time":0.02883029046},
{"learn":[3.197467568],"iteration":895,"passed_time":0.2459479031,"remaining_time":0.02854752446},
{"learn":[3.195838544],"iteration":896,"passed_time":0.2461503184,"remaining_time":0.02826475228},
{"learn":[3.195671746],"iteration":897,"passed_time":0.2464310665,"remaining_time":0.02799105655},
{"learn":[3.194213094],"iteration":898,"passed_time":0.2467114396,"remaining_time":0.02771730301},
{"learn":[3.192884691],"iteration":899,"passed_time":0.2469428548,"remaining_time":0.02743809497},
{"learn":[3.188364239],"iteration":900,"passed_time":0.2472895608,"remaining_time":0.02717166095},
{"learn":[3.185219478],"iteration":901,"passed_time":0.2475391425,"remaining_time":0.02689449663},
{"learn":[3.184120387],"iteration":902,"passed_time":0.2477579327,"remaining_time":0.02661408579},
{"learn":[3.183725321],"iteration":903,"passed_time":0.2479905561,"remaining_time":0.0263352803},
{"learn":[3.181264554],"iteration":904,"passed_time":0.2481945964,"remaining_time":0.02605357642},
{"learn":[3.180741589],"iteration":905,"passed_time":0.2483899285,"remaining_time":0.02577114048},
{"learn":[3.179782639],"iteration":906,"passed_time":0.2486447601,"remaining_time":0.02549499745},
{"learn":[3.176377564],"iteration":907,"passed_time":0.2488399255,"remaining_time":0.02521285588},
{"learn":[3.174078182],"iteration":908,"passed_time":0.2490183826,"remaining_time":0.02492923302},
{"learn":[3.171242379],"iteration":909,"passed_time":0.2492225896,"remaining_time":0.02464838798},
{"learn":[3.170421012],"iteration":910,"passed_time":0.2494507964,"remaining_time":0.02437005585},
{"learn":[3.170087224],"iteration":911,"passed_time":0.2497010031,"remaining_time":0.02409395644},
{"learn":[3.167303059],"iteration":912,"passed_time":0.2498769186,"remaining_time":0.02381083452},
{"learn":[3.16705966],"iteration":913,"passed_time":0.2500556674,"remaining_time":0.02352821378},
{"learn":[3.165667683],"iteration":914,"passed_time":0.2502485411,"remaining_time":0.02324713223},
{"learn":[3.164689733],"iteration":915,"passed_time":0.2504898311,"remaining_time":0.0229706832},
{"learn":[3.163311455],"iteration":916,"passed_time":0.250705038,"remaining_time":0.02269195001},
{"learn":[3.159425016],"iteration":917,"passed_time":0.2509308699,"remaining_time":0.02241430428},
{"learn":[3.159327058],"iteration":918,"passed_time":0.2511225769,"remaining_time":0.02213376358},
{"learn":[3.15819426],"iteration":919,"passed_time":0.251311659,"remaining_time":0.02185318774},
{"learn":[3.157086603],"iteration":920,"passed_time":0.2514947828,"remaining_time":0.0215722995},
{"learn":[3.153354154],"iteration":921,"passed_time":0.2516904065,"remaining_time":0.02129268081},
{"learn":[3.153261317],"iteration":922,"passed_time":0.2518769052,"remaining_time":0.02101248288},
{"learn":[3.153168454],"iteration":923,"passed_time":0.2520805705,"remaining_time":0.02073389974},
{"learn":[3.152080399],"iteration":924,"passed_time":0.2522688609,"remaining_time":0.02045423197},
{"learn":[3.151635144],"iteration":925,"passed_time":0.2525235259,"remaining_time":0.02018006579},
{"learn":[3.147762655],"iteration":926,"passed_time":0.2527545244,"remaining_time":0.01990407797},
{"learn":[3.147172317],"iteration":927,"passed_time":0.2529778979,"remaining_time":0.01962759553},
{"learn":[3.146254125],"iteration":928,"passed_time":0.2531546884,"remaining_time":0.01934766725},
{"learn":[3.144869828],"iteration":929,"passed_time":0.2533478954,"remaining_time":0.01906919643},
{"learn":[3.143466218],"iteration":930,"passed_time":0.253560144,"remaining_time":0.01879232002},
{"learn":[3.141919643],"iteration":931,"passed_time":0.2537556427,"remaining_time":0.0185143602},
{"learn":[3.141054135],"iteration":932,"passed_time":0.2539746829,"remaining_time":0.01823826769},
{"learn":[3.139390417],"iteration":933,"passed_time":0.2541883482,"remaining_time":0.01796191754},
{"learn":[3.139025283],"iteration":934,"passed_time":0.2543855552,"remaining_time":0.01768455731},
{"learn":[3.137824183],"iteration":935,"passed_time":0.2545834289,"remaining_time":0.01740741394},
{"learn":[3.135620453],"iteration":936,"passed_time":0.254807594,"remaining_time":0.0171322075},
{"learn":[3.13443178],"iteration":937,"passed_time":0.2549989678,"remaining_time":0.01685494243},
{"learn":[3.132765713],"iteration":938,"passed_time":0.2552005498,"remaining_time":0.01657852347},
{"learn":[3.131434124],"iteration":939,"passed_time":0.2553845902,"remaining_time":0.01630114405},
{"learn":[3.128384262],"iteration":940,"passed_time":0.2555845472,"remaining_time":0.01602496098},
{"learn":[3.128120455],"iteration":941,"passed_time":0.255767046,"remaining_time":0.01574786483},
{"learn":[3.126314615],"iteration":942,"passed_time":0.2559467114,"remaining_time":0.01547079804},
{"learn":[3.125409666],"iteration":943,"passed_time":0.2561559601,"remaining_time":0.01519569255},
{"learn":[3.123072589],"iteration":944,"passed_time":0.2563497921,"remaining_time":0.01491982917},
{"learn":[3.122921099],"iteration":945,"passed_time":0.2566165403,"remaining_time":0.01464830146},
{"learn":[3.122182662],"iteration":946,"passed_time":0.2568049974,"remaining_time":0.01437240218},
{"learn":[3.120040951],"iteration":947,"passed_time":0.2570245793,"remaining_time":0.01409839464},
{"learn":[3.118767799],"iteration":948,"passed_time":0.2572724943,"remaining_time":0.01382602446},
{"learn":[3.118203218],"iteration":949,"passed_time":0.2574564514,"remaining_time":0.01355033955},
{"learn":[3.116343362],"iteration":950,"passed_time":0.2576492418,"remaining_time":0.01327530268},
{"learn":[3.11480829],"iteration":951,"passed_time":0.2578346989,"remaining_time":0.01300006885},
{"learn":[3.112607903],"iteration":952,"passed_time":0.2580311142,"remaining_time":0.01272556387},
{"learn":[3.111661241],"iteration":953,"passed_time":0.258214863,"remaining_time":0.01245061184},
{"learn":[3.110249676],"iteration":954,"passed_time":0.2583998201,"remaining_time":0.01217590775},
{"learn":[3.107333579],"iteration":955,"passed_time":0.2586249436,"remaining_time":0.01190324008},
{"learn":[3.107149851],"iteration":956,"passed_time":0.2588422755,"remaining_time":0.01163032168},
{"learn":[3.106867336],"iteration":957,"passed_time":0.2590467741,"remaining_time":0.01135695669},
{"learn":[3.10364681],"iteration":958,"passed_time":0.2593066891,"remaining_time":0.01108610454},
{"learn":[3.102703811],"iteration":959,"passed_time":0.2595206043,"remaining_time":0.01081335851},
{"learn":[3.101469264],"iteration":960,"passed_time":0.2597335196,"remaining_time":0.01054069434},
{"learn":[3.09863569],"iteration":961,"passed_time":0.2599490598,"remaining_time":0.01026825808},
{"learn":[3.09645939],"iteration":962,"passed_time":0.2601556001,"remaining_time":0.009995594188},
{"learn":[3.096240186],"iteration":963,"passed_time":0.2603385572,"remaining_time":0.009722186783},
{"learn":[3.094838828],"iteration":964,"passed_time":0.2605413892,"remaining_time":0.00944968769},
{"learn":[3.094176802],"iteration":965,"passed_time":0.2607411378,"remaining_time":0.009177224313},
{"learn":[3.093182279],"iteration":966,"passed_time":0.2609304282,"remaining_time":0.008904554428},
{"learn":[3.090150687],"iteration":967,"passed_time":0.2611555934,"remaining_time":0.008633242757},
{"learn":[3.088612829],"iteration":968,"passed_time":0.261363967,"remaining_time":0.008361489141},
{"learn":[3.087153684],"iteration":969,"passed_time":0.2615799239,"remaining_time":0.00809010074},
{"learn":[3.085866843],"iteration":970,"passed_time":0.2618211723,"remaining_time":0.007819581871},
{"learn":[3.082669094],"iteration":971,"passed_time":0.2620664207,"remaining_time":0.007549238456},
{"learn":[3.081047548],"iteration":972,"passed_time":0.262314794,"remaining_time":0.007279033339},
{"learn":[3.079684322],"iteration":973,"passed_time":0.2625128344,"remaining_time":0.007007529459},
{"learn":[3.07613431],"iteration":974,"passed_time":0.2627010831,"remaining_time":0.006735925208},
{"learn":[3.074005935],"iteration":975,"passed_time":0.2629082901,"remaining_time":0.006464957952},
{"learn":[3.072988853],"iteration":976,"passed_time":0.263113247,"remaining_time":0.006194068252},
{"learn":[3.072344268],"iteration":977,"passed_time":0.2633135374,"remaining_time":0.005923208407},
{"learn":[3.070654438],"iteration":978,"passed_time":0.2635441608,"remaining_time":0.005653143389},
{"learn":[3.069724506],"iteration":979,"passed_time":0.2639054084,"remaining_time":0.005385824662},
{"learn":[3.067763166],"iteration":980,"passed_time":0.2641338652,"remaining_time":0.005115742548},
{"learn":[3.066737893],"iteration":981,"passed_time":0.2643155307,"remaining_time":0.004844887528},
{"learn":[3.065248174],"iteration":982,"passed_time":0.2645207793,"remaining_time":0.004574621819},
{"learn":[3.063186837],"iteration":983,"passed_time":0.2647095281,"remaining_time":0.004304219969},
{"learn":[3.062880371],"iteration":984,"passed_time":0.2650419425,"remaining_time":0.004036171713},
{"learn":[3.061288645],"iteration":985,"passed_time":0.2652366079,"remaining_time":0.003766037029},
{"learn":[3.059970575],"iteration":986,"passed_time":0.2654187733,"remaining_time":0.003495890632},
{"learn":[3.059576341],"iteration":987,"passed_time":0.265621897,"remaining_time":0.003226176886},
{"learn":[3.058175919],"iteration":988,"passed_time":0.2658044791,"remaining_time":0.002956369333},
{"learn":[3.056830702],"iteration":989,"passed_time":0.2660090194,"remaining_time":0.002686959792},
{"learn":[3.056336579],"iteration":990,"passed_time":0.2662104764,"remaining_time":0.002417653166},
{"learn":[3.055810414],"iteration":991,"passed_time":0.2664096001,"remaining_time":0.002148464517},
{"learn":[3.055476518],"iteration":992,"passed_time":0.2665878489,"remaining_time":0.001879269831},
{"learn":[3.053331734],"iteration":993,"passed_time":0.266772431,"remaining_time":0.001610296364},
{"learn":[3.050890374],"iteration":994,"passed_time":0.2669890129,"remaining_time":0.001341653331},
{"learn":[3.04972623],"iteration":995,"passed_time":0.2671719283,"remaining_time":0.001072979632},
{"learn":[3.047217327],"iteration":996,"passed_time":0.2673898852,"remaining_time":0.0008045834058},
{"learn":[3.047155483],"iteration":997,"passed_time":0.2675633424,"remaining_time":0.0005361990829},
{"learn":[3.04430671],"iteration":998,"passed_time":0.2678181324,"remaining_time":0.0002680862186},
{"learn":[3.042664195],"iteration":999,"passed_time":0.2680459642,"remaining_time":0}
]}